Workbook
Name Access_Points: #REF!
Name Cabinets: #REF!
Name CustomerView: #REF!
Name Desktop_Pc: #REF!
Name Digital_Repository: #REF!
Name Installation___Support: #REF!
Name Managed_Capacity: #REF!
Name Network_O_M: #REF!
Name QTO_DB: Table1[]
Name Routers_Microtik: #REF!
Name Solar_Panels: #REF!
Name VSAT: #REF!
Name Web_Filetring: #REF!

Sheet QTO
A1: QTO PRONATEL-EPAD SELVA
C2: 5
C3: 5
C4: 5 | H4: PRICE | I4: COST | J4: MARGIN | L4: Infraestructure | M4: =#REF!+#REF!+#REF!+#REF!+#REF!+#REF!+#REF!+#REF!+#REF! -> #REF!
C5: 5 | D5: =#REF!+#REF! -> #REF! | G5: CAPEX | H5: =SUMIF(A23:A132,"CAPEX",H23:H132) -> #REF! | I5: =SUMIF(A23:A132,"CAPEX",J23:J132) -> #REF! | J5: =1-(I5/H5) -> #REF! | L5: One Time Services | M5: =#REF!-J84 -> #REF!
C6: 5 | D6: =#REF!+#REF! -> #REF! | G6: OPEX | H6: =SUMIF(A23:A132,"OPEX",H23:H132) -> #REF! | I6: =SUMIF(A23:A132,"OPEX",J23:J132) -> #REF! | J6: =1-(I6/H6) -> #REF! | L6: Installation + Site Survey + Materials Sites Ka Band | M6: =J84 -> #REF!
C7: 5 | D7: =D5+D6 -> #REF! | H7: =SUM(H5:H6) -> #REF! | I7: =SUM(I5:I6) -> #REF! | J7: =1-(I7/H7) -> #REF! | L7: One Time Network and Management Operations | M7: =#REF! -> #REF!
C8: 5 | D8: 0.05 | L8: Recurring services - Management, call out | M8: =#REF! -> #REF!
C9: 5 | L9: Space Segment Ka - T19V & SES-17 | M9: =#REF! -> #REF!
C10: 5 | D10: =D5*2.5 -> #REF! | L10: Penalties | M10: =#REF! -> #REF!
C11: 5 | D11: =D6*2.5 -> #REF!
C12: 5 | D12: =D10+D11 -> #REF! | H12: Price x Site x Month | I12: Cost x Site x Month | J12: MARGIN
C13: 5 | D13: =D12/D7 -> #REF! | H13: =H7/D7/D18 -> #REF! | I13: =I7/D7/D18 -> #REF! | J13: =1-(I13/H13) -> #REF!
C14: 5 | D14: 3.8
C15: 5 | D15: =G26+G27+G28+G32 -> 745.41429
C16: 5 | D16: 125
C17: 5 | D17: 52
C18: 5 | D18: 24
C19: 5 | D19: 0.01
C20: 5 | D20: =4950/D14 -> 1302.6316
C21: 5
A22: CAPEX | C22: 5
A23: Hughes Equipment
A24: Type | C24: Manufacturer Part # | D24: Product Code | E24: Description | F24: Qty | G24: Unit Price | H24: Ext. Price | I24: Unit Cost | J24: Ext. Cost | K24: Profit Margin | L24: Owner | M24: Notes
A25: Baseline Equipment
A26: CAPEX | B26: Hughes Eq. | C26: 1505216-0332 | D26: HT2010 | E26: HT2010 Consumer Broadband Satellite Router, Ka Band only | F26: =$D$7*(1+D8) -> #REF! | G26: =I26/0.7 -> 109.71429 | H26: =F26*G26 -> #REF! | I26: 76.8 | J26: =F26*I26 -> #REF! | K26: =1-(J26/H26) -> #REF! | L26: HNS
A27: CAPEX | B27: Hughes Eq. | C27: 1506307-0001+1506307-0101 | D27: AN-120-SG-P1 + AN-120-SG-P2 | E27: 1.2m Ka-Band antenna, Single IFL | F27: 35 | G27: =I27/0.7 -> 426.52857 | H27: =F27*G27 -> 14928.5 | I27: 298.57 | J27: =F27*I27 -> 10449.95 | K27: =1-(J27/H27) -> 0.3 | L27: HNS
A28: CAPEX | B28: Hughes Eq. | C28: 1506689-1004 | D28: HB220-L | E28: 3W Multi-mode radio, Ka-Band, RHCP | F28: =$D$7 -> #REF! | G28: =I28/0.7 -> 138.45714 | H28: =F28*G28 -> #REF! | I28: 96.92 | J28: =F28*I28 -> #REF! | K28: =1-(J28/H28) -> #REF! | L28: HNS
A29: CAPEX | B29: Hughes Eq. | C29: 1506560-0012+1506561-0011 | D29: AN-90-KA1-NL-4PK + AN-90-KA2-4PK | E29: 90cm Ka-Band antenna, Single IFL, 4 PK- 4 antennas | F29: 80 | G29: =I29/0.7 -> 410.3 | H29: =F29*G29 -> 32824 | I29: 287.21 | J29: =F29*I29 -> 22976.8 | K29: =1-(J29/H29) -> 0.3 | L29: HNS
A30: CAPEX | B30: Hughes Eq. | C30: 1506560-0022+ 1506561-0021 | D30: AN-90-KA1-NL-1PK + AN-90-KA2-1PK | E30: 90cm Ka-Band antenna, Single IFL, 1 PK | F30: 1 | G30: =I30/0.7 -> 129.4 | H30: =F30*G30 -> 129.4 | I30: 90.58 | J30: =F30*I30 -> 90.58 | K30: =1-(J30/H30) -> 0.3 | L30: HNS
A31: CAPEX | B31: Hughes Eq. | D31: Antenna Mast | E31: Trimast Mount for 74cm and 90cm antenna | F31: =F28-F32 -> #REF! | G31: =I31/0.7 -> 20 | H31: =F31*G31 -> #REF! | I31: 14 | J31: =F31*I31 -> #REF! | K31: =1-(J31/H31) -> #REF! | L31: HNS
A32: CAPEX | B32: Hughes Eq. | C32: 611604104 | D32: Antenna Mast | E32: 1.2m Ka antenna tri-mast mount | F32: 35 | G32: =I32/0.7 -> 70.714286 | H32: =F32*G32 -> 2475 | I32: 49.5 | J32: =F32*I32 -> 1732.5 | K32: =1-(J32/H32) -> 0.3 | L32: HNS
E33: Subtotal Baseline Equipment | H33: =SUM(H26:H32) -> #REF! | J33: =SUM(J26:J32) -> #REF! | K33: =1-(J33/H33) -> #REF!
A34: Spares (20 kits vandalism and 5% for operations)
A35: CAPEX | B35: Hughes Eq. | C35: 1505216-0332 | D35: HT2010 | E35: HT2010 Consumer Broadband Satellite Router, Ka Band only | F35: =ROUNDUP($D$8*$D$7,0) -> #REF! | G35: =I35/0.7 -> 109.71429 | H35: =F35*G35 -> #REF! | I35: 76.8 | J35: =F35*I35 -> #REF! | K35: =1-(J35/H35) -> #REF! | L35: HNS
A36: CAPEX | B36: Hughes Eq. | C36: 1506307-0001+1506307-0101 | D36: AN-120-SG-P1 + AN-120-SG-P2 | E36: 1.2m Ka-Band antenna, Single IFL | F36: 3 | G36: =I36/0.7 -> 426.52857 | H36: =F36*G36 -> 1279.5857 | I36: 298.57 | J36: =F36*I36 -> 895.71 | K36: =1-(J36/H36) -> 0.3 | L36: HNS
A37: CAPEX | B37: Hughes Eq. | C37: 1506689-1004 | D37: HB220-L | E37: 3W Multi-mode radio, Ka-Band, RHCP | F37: =ROUNDUP($D$8*$D$7,0) -> #REF! | G37: =I37/0.7 -> 138.45714 | H37: =F37*G37 -> #REF! | I37: 96.92 | J37: =F37*I37 -> #REF! | K37: =1-(J37/H37) -> #REF! | L37: HNS
A38: CAPEX | B38: Hughes Eq. | C38: 1506560-0012+1506561-0011 | D38: AN-90-KA1-NL-4PK + AN-90-KA2-4PK | E38: 90cm Ka-Band antenna, Single IFL, 4 PK- 4 antennas | F38: 4 | G38: =I38/0.7 -> 410.3 | H38: =F38*G38 -> 1641.2 | I38: 287.21 | J38: =F38*I38 -> 1148.84 | K38: =1-(J38/H38) -> 0.3 | L38: HNS
A39: CAPEX | B39: Hughes Eq. | C39: 1506560-0022+ 1506561-0021 | D39: AN-90-KA1-NL-1PK + AN-90-KA2-1PK | E39: 90cm Ka-Band antenna, Single IFL, 1 PK | F39: 0 | G39: =I39/0.7 -> 129.4 | H39: =F39*G39 -> 0 | I39: 90.58 | J39: =F39*I39 -> 0 | K39: =1-(J39/H39) -> #DIV/0! | L39: HNS
A40: CAPEX | B40: Hughes Eq. | D40: Antenna Mast | E40: Trimast Mount for 74cm and 90cm antenna | F40: 15 | G40: =I40/0.7 -> 20 | H40: =F40*G40 -> 300 | I40: 14 | J40: =F40*I40 -> 210 | K40: =1-(J40/H40) -> 0.3 | L40: HNS
A41: CAPEX | B41: Hughes Eq. | C41: 611604104 | D41: Antenna Mast | E41: 1.2m Ka antenna tri-mast mount | F41: 3 | G41: =I41/0.7 -> 70.714286 | H41: =F41*G41 -> 212.14286 | I41: 49.5 | J41: =F41*I41 -> 148.5 | K41: =1-(J41/H41) -> 0.3 | L41: HNS
E42: Subtotal Spares | H42: =SUM(H35:H41) -> #REF! | J42: =SUM(J35:J41) -> #REF! | K42: =1-(J42/H42) -> #REF!
A43: Summary Hughes Equipment | H43: =H42+H33 -> #REF! | J43: =J42+J33 -> #REF! | K43: =1-(J43/H43) -> #REF!
A44: Third Party Equipment
A45: Type | C45: Vendor | D45: Product Code | E45: Description | F45: Qty | G45: Unit Price | H45: Ext. Price | I45: Unit Cost | J45: Ext. Cost | K45: Profit Margin | L45: Owner | M45: Notes
A46: SOLAR PANELS
A47: CAPEX | B47: 3rd Party Eq. | E47: Solar Panel | F47: =D7 -> #REF! | G47: =I47/0.75 -> #REF! | H47: =F47*G47 -> #REF! | I47: =#REF!+#REF! -> #REF! | J47: =F47*I47 -> #REF! | K47: =1-(J47/H47) -> #REF! | L47: HDP
A48: CAPEX | B48: 3rd Party Eq. | E48: Spare Solar Panel | F48: =ROUNDUP($D$8*$D$7,0) -> #REF! | G48: =I48/0.75 -> #REF! | H48: =F48*G48 -> #REF! | I48: =#REF!+#REF! -> #REF! | J48: =F48*I48 -> #REF! | K48: =1-(J48/H48) -> #REF! | L48: HDP
E49: Subtotal Solar Panels | H49: =SUM(H46:H48) -> #REF! | J49: =SUM(J46:J48) -> #REF! | K49: =1-(J49/H49) -> #REF!
A50: CABINETS
A51: CAPEX | B51: 3rd Party Eq. | E51: Cabinet Outdoor | F51: =$D$7 -> #REF! | G51: =I51/0.75 -> #REF! | H51: =F51*G51 -> #REF! | I51: =#REF! -> #REF! | J51: =F51*I51 -> #REF! | K51: =1-(J51/H51) -> #REF! | L51: HDP
A52: CAPEX | B52: 3rd Party Eq. | E52: Spare Cabinets | F52: =ROUNDUP($D$8*$D$7,0) -> #REF! | G52: =I52/0.75 -> #REF! | H52: =F52*G52 -> #REF! | I52: =#REF! -> #REF! | J52: =F52*I52 -> #REF! | K52: =1-(J52/H52) -> #REF! | L52: HDP
E53: Subtotal Cabinets | H53: =SUM(H50:H52) -> #REF! | J53: =SUM(J50:J52) -> #REF! | K53: =1-(J53/H53) -> #REF!
A54: ROUTERS MIKROTIK
A55: CAPEX | B55: 3rd Party Eq. | C55: MIKROTIK | D55: RB760IGS | E55: 5x Gigabit Ethernet, SFP, Dual Core 880MHz CPU, 256MB RAM, USB, microSD, RouterOS L4, IPsec hardware encryption support and The Dude server package | F55: =$D$7 -> #REF! | G55: =I55/0.75 -> #REF! | H55: =F55*G55 -> #REF! | I55: =#REF! -> #REF! | J55: =F55*I55 -> #REF! | K55: =1-(J55/H55) -> #REF! | L55: HDP
A56: CAPEX | B56: 3rd Party Eq. | C56: MIKROTIK | D56: RB760IGS | E56: 5x Gigabit Ethernet, SFP, Dual Core 880MHz CPU, 256MB RAM, USB, microSD, RouterOS L4, IPsec hardware encryption support and The Dude server package (20 kits vandalism and 5% for operations) | F56: =ROUNDUP($D$8*$D$7,0) -> #REF! | G56: =I56/0.75 -> #REF! | H56: =F56*G56 -> #REF! | I56: =#REF! -> #REF! | J56: =F56*I56 -> #REF! | K56: =1-(J56/H56) -> #REF! | L56: HDP
E57: Subtotal Routers | H57: =SUM(H54:H56) -> #REF! | J57: =SUM(J54:J56) -> #REF! | K57: =1-(J57/H57) -> #REF!
A58: DESKTOP COMPUTER
A59: CAPEX | B59: 3rd Party Eq. | E59: Computadora para Monitoreo | F59: 1 | G59: =I59/0.75 -> 6666.6667 | H59: =F59*G59 -> 6666.6667 | I59: 5000 | J59: =F59*I59 -> 5000 | K59: =1-(J59/H59) -> 0.25 | L59: HDP
E60: Subtotal Desktop Computer | H60: =SUM(H58:H59) -> 6666.6667 | J60: =SUM(J58:J59) -> 5000 | K60: =1-(J60/H60) -> 0.25
A61: IBOSS-WEB FILTERING SOLUTION
A62: CAPEX | B62: 3rd Party Eq. | E62: FORTINET ITEM 1 | F62: 0 | G62: =I62/0.75 -> #REF! | H62: =F62*G62*$D$18 -> #REF! | I62: =#REF! -> #REF! | J62: =F62*I62*$D$18 -> #REF! | K62: =1-(J62/H62) -> #REF! | L62: HDP
A63: CAPEX | B63: 3rd Party Eq. | E63: FORTINET ITEM 2 | F63: 0 | G63: =I63/0.75 -> #REF! | H63: =F63*G63*$D$18 -> #REF! | I63: =#REF! -> #REF! | J63: =F63*I63*$D$18 -> #REF! | K63: =1-(J63/H63) -> #REF! | L63: HDP
A64: CAPEX | B64: 3rd Party Eq. | E64: FORTINET ITEM 3 | F64: 0 | G64: =I64/0.75 -> #REF! | H64: =F64*G64*$D$18 -> #REF! | I64: =#REF! -> #REF! | J64: =F64*I64*$D$18 -> #REF! | K64: =1-(J64/H64) -> #REF! | L64: HDP
A65: CAPEX | B65: 3rd Party Eq. | E65: FORTINET ITEM 4 | F65: 1 | G65: =I65/0.75 -> #REF! | H65: =F65*G65 -> #REF! | I65: =#REF! -> #REF! | J65: =F65*I65 -> #REF! | K65: =1-(J65/H65) -> #REF! | L65: HDP
A66: CAPEX | B66: 3rd Party Eq. | E66: FORTINET ITEM 5 | F66: 1 | G66: =I66/0.75 -> #REF! | H66: =F66*G66 -> #REF! | I66: =#REF! -> #REF! | J66: =F66*I66 -> #REF! | K66: =1-(J66/H66) -> #REF! | L66: HDP
A67: CAPEX | B67: 3rd Party Eq. | E67: FORTINET ALL ITEMS | F67: 0 | G67: =I67/0.75 -> #REF! | H67: =F67*G67 -> #REF! | I67: =#REF! -> #REF! | J67: =F67*I67 -> #REF! | K67: =1-(J67/H67) -> #REF! | L67: HDP
E68: Subtotal IBOSS Web Filtering Solution | H68: =SUM(H62:H67) -> #REF! | J68: =SUM(J62:J67) -> #REF! | K68: =1-(J68/H68) -> #REF!
A69: ACCESS POINTS
A70: CAPEX | B70: 3rd Party Eq. | C70: CAMBIUM | E70: Outdoor Dual radio WiFi 6 AP Omni 2x2, GbE. RW | F70: =D7*2 -> #REF! | G70: =I70/0.75 -> #REF! | H70: =F70*G70 -> #REF! | I70: =#REF! -> #REF! | J70: =F70*I70 -> #REF! | K70: =1-(J70/H70) -> #REF! | L70: HDP
A71: CAPEX | B71: 3rd Party Eq. | C71: CAMBIUM | E71: PoE, 60W, 56V, 5GbE DC Injector, Indoor, Energy Level 6 Supply, accepts C5 connector | F71: =D7*2 -> #REF! | G71: =I71/0.75 -> #REF! | H71: =F71*G71 -> #REF! | I71: =#REF! -> #REF! | J71: =F71*I71 -> #REF! | K71: =1-(J71/H71) -> #REF! | L71: HDP
A72: CAPEX | B72: 3rd Party Eq. | C72: CAMBIUM | E72: AC line cord, US Type B, 720mm, C5 connector | F72: =D7*2 -> #REF! | G72: =I72/0.75 -> #REF! | H72: =F72*G72 -> #REF! | I72: =#REF! -> #REF! | J72: =F72*I72 -> #REF! | K72: =1-(J72/H72) -> #REF! | L72: HDP
A73: CAPEX | B73: 3rd Party Eq. | C73: CAMBIUM | E73: XMS-Cloud 3-year subscription for Education: 2 and 3-radio AP with all EasyPass modules and Cambium Care Advanced Support | F73: =D7*2 -> #REF! | G73: =I73/0.75 -> #REF! | H73: =F73*G73 -> #REF! | I73: =#REF! -> #REF! | J73: =F73*I73 -> #REF! | K73: =1-(J73/H73) -> #REF! | L73: HDP
A74: CAPEX | B74: 3rd Party Eq. | C74: CAMBIUM | E74: Outdoor Dual radio WiFi 6 AP Omni 2x2, GbE. RW | F74: =ROUNDUP($D$8*$D$7,0)*2 -> #REF! | G74: =I74/0.75 -> #REF! | H74: =F74*G74 -> #REF! | I74: =#REF! -> #REF! | J74: =F74*I74 -> #REF! | K74: =1-(J74/H74) -> #REF! | L74: HDP
A75: CAPEX | B75: 3rd Party Eq. | C75: CAMBIUM | E75: PoE, 60W, 56V, 5GbE DC Injector, Indoor, Energy Level 6 Supply, accepts C5 connector | F75: =ROUNDUP($D$8*$D$7,0)*2 -> #REF! | G75: =I75/0.75 -> #REF! | H75: =F75*G75 -> #REF! | I75: =#REF! -> #REF! | J75: =F75*I75 -> #REF! | K75: =1-(J75/H75) -> #REF! | L75: HDP
A76: CAPEX | B76: 3rd Party Eq. | C76: CAMBIUM | E76: AC line cord, US Type B, 720mm, C5 connector | F76: =ROUNDUP($D$8*$D$7,0)*2 -> #REF! | G76: =I76/0.75 -> #REF! | H76: =F76*G76 -> #REF! | I76: =#REF! -> #REF! | J76: =F76*I76 -> #REF! | K76: =1-(J76/H76) -> #REF! | L76: HDP
E77: Subtotal Access Points | H77: =SUM(H70:H76) -> #REF! | J77: =SUM(J70:J76) -> #REF! | K77: =1-(J77/H77) -> #REF!
A78: ONE TIME SERVICES
A79: CAPEX | B79: 3rd Party Eq. | E79: Movings or Relocation 10% (Unistallation & re installation) | F79: =ROUNDUP(10%*$D$7,0) -> #REF! | G79: =I79/0.75 -> #REF! | H79: =F79*G79 -> #REF! | I79: =#REF!+#REF! -> #REF! | J79: =F79*I79 -> #REF! | K79: =1-(J79/H79) -> #REF! | L79: HDP
A80: CAPEX | B80: 3rd Party Eq. | E80: Logistics (Storage center) | F80: =ROUNDUP(110%*$D$7,0) -> #REF! | G80: =I80/0.75 -> 6.6666667 | H80: =F80*G80*6 -> #REF! | I80: 5 | J80: =F80*I80*6 -> #REF! | K80: =1-(J80/H80) -> #REF! | L80: HDP
A81: CAPEX | B81: 3rd Party Eq. | E81: Local Training to 2 people of the EPAD about process to verify the terminal | F81: 2 | G81: =I81/0.75 -> 2133.3333 | H81: =F81*G81 -> 4266.6667 | I81: 1600 | J81: =F81*I81 -> 3200 | K81: =1-(J81/H81) -> 0.25 | L81: HDP
A82: CAPEX | B82: 3rd Party Eq. | E82: Local training about the monitoring tool and web filtering tool | F82: 1 | G82: =I82/0.75 -> 4666.6667 | H82: =F82*G82 -> 4666.6667 | I82: 3500 | J82: =F82*I82 -> 3500 | K82: =1-(J82/H82) -> 0.25 | L82: HDP
A83: CAPEX | B83: 3rd Party Eq. | E83: Failed visits during installation | F83: =ROUNDUP(5%*$D$7,0) -> #REF! | G83: =I83/0.75 -> 2000 | H83: =F83*G83 -> #REF! | I83: 1500 | J83: =F83*I83 -> #REF! | K83: =1-(J83/H83) -> #REF! | L83: HDP
A84: CAPEX | B84: 3rd Party Eq. | E84: Installation + Site Survey + Materials Sites Ka Band | F84: =$D$7 -> #REF! | G84: =I84/0.75 -> #REF! | H84: =F84*G84 -> #REF! | I84: =#REF!+#REF!+#REF!+#REF! -> #REF! | J84: =F84*I84 -> #REF! | K84: =1-(J84/H84) -> #REF! | L84: HDP
E85: Subtotal One Time Services | H85: =SUM(H79:H84) -> #REF! | J85: =SUM(J79:J84) -> #REF! | K85: =1-(J85/H85) -> #REF!
A86: One time Network Operations and Management setup
A87: CAPEX | B87: 3rd Party Eq. | E87: Transportation Hughes | F87: 1 | G87: =I87/0.75 -> #REF! | H87: =F87*G87 -> #REF! | I87: =#REF!*$D$7/1376 -> #REF! | J87: =F87*I87 -> #REF! | K87: =1-(J87/H87) -> #REF! | L87: HNS | M87: VSAT
A88: CAPEX | B88: 3rd Party Eq. | E88: Development and Implementation of Speed ​​Tests | F88: 1 | G88: =I88/0.7 -> 214285.71 | H88: =F88*G88 -> 214285.71 | I88: 150000 | J88: =F88*I88 -> 150000 | K88: =1-(J88/H88) -> 0.3 | L88: HNS | M88: GW-INFRA
A89: CAPEX | B89: 3rd Party Eq. | E89: Monitoring Platform for Links | F89: =D7 -> #REF! | G89: =I89/0.75 -> #REF! | H89: =F89*G89 -> #REF! | I89: =#REF! -> #REF! | J89: =F89*I89 -> #REF! | K89: =1-(J89/H89) -> #REF! | L89: HNS | M89: GW-INFRA
A90: CAPEX | B90: 3rd Party Eq. | E90: Dedicated FTE from Germantown | F90: 6 | G90: =I90/0.7 -> 28571.429 | H90: =F90*G90 -> 171428.57 | I90: 20000 | J90: =F90*I90 -> 120000 | K90: =1-(J90/H90) -> 0.3 | L90: HNS | M90: GW-INFRA
A91: CAPEX | B91: 3rd Party Eq. | E91: Monitoring Plataform | F91: 1 | G91: =I91/0.75 -> 266666.67 | H91: =F91*G91 -> 266666.67 | I91: 200000 | J91: =F91*I91 -> 200000 | K91: =1-(J91/H91) -> 0.25 | L91: HNS | M91: GW-INFRA
A92: CAPEX | B92: 3rd Party Eq. | E92: Server for SpeedTest - HP DL360 | F92: 8 | G92: =I92/0.75 -> 10133.333 | H92: =F92*G92 -> 81066.667 | I92: 7600 | J92: =F92*I92 -> 60800 | K92: =1-(J92/H92) -> 0.25
E93: Subtotal One Time NW Ops and Mgmnt | H93: =SUM(H87:H92) -> #REF! | J93: =SUM(J87:J92) -> #REF! | K93: =1-(J93/H93) -> #REF!
A94: Digital Repositoriy
A95: CAPEX | B95: 3rd Party Eq. | E95: Edulink Mini Servidor Industrial | F95: =$D$7 -> #REF! | G95: =I95/0.75 -> 333.33333 | H95: =F95*G95 -> #REF! | I95: 250 | J95: =F95*I95 -> #REF! | K95: =1-(J95/H95) -> #REF! | L95: HDP
A96: CAPEX | B96: 3rd Party Eq. | E96: Edulink Mini Servidor Industrial - Spare | F96: =ROUNDUP($D$8*$D$7,0) -> #REF! | G96: =I96/0.75 -> 333.33333 | H96: =F96*G96 -> #REF! | I96: 250 | J96: =F96*I96 -> #REF! | K96: =1-(J96/H96) -> #REF! | L96: HDP
A97: CAPEX | B97: 3rd Party Eq. | E97: Edulink Implementation | F97: 1 | G97: =I97/0.75 -> #REF! | H97: =F97*G97 -> #REF! | I97: =#REF! -> #REF! | J97: =F97*I97 -> #REF! | K97: =1-(J97/H97) -> #REF! | L97: HDP
A98: CAPEX | B98: 3rd Party Eq. | E98: Support 2 years | F98: 1 | G98: =I98/0.75 -> #REF! | H98: =F98*G98 -> #REF! | I98: =#REF! -> #REF! | J98: =F98*I98 -> #REF! | K98: =1-(J98/H98) -> #REF! | L98: HDP
A99: CAPEX | B99: 3rd Party Eq. | E99: Software Edulink | F99: 1 | G99: =I99/0.75 -> #REF! | H99: =F99*G99 -> #REF! | I99: =#REF! -> #REF! | J99: =F99*I99 -> #REF! | K99: =1-(J99/H99) -> #REF! | L99: HDP
E100: Subtotal Digital Repository | H100: =SUM(H95:H99) -> #REF! | J100: =SUM(J95:J99) -> #REF! | K100: =1-(J100/H100) -> #REF!
...

Sheet QTO DB
A1: Inputs
A2: Client:
B3: Country
B4: Proposal Manager: | F4: PRICE | G4: COST | H4: MARGIN
A5: HUGHES T19 Number of Sites | C5: 1 | E5: CAPEX | F5: =SUMIF(A24:A25,"CAPEX",M24:M25) -> 0 | G5: =SUMIF(A24:A25,"CAPEX",O24:O25) -> 0 | H5: =1-(G5/F5) -> #DIV/0! | AZ5: Financed? | BA5: Unit of Measure | BB5: Type | BC5: Category | BD5: Subcategory
A6: Sites out of coverage | C6: 0 | E6: OPEX | F6: =SUMIF(A24:A25,"OPEX",M24:M25) -> 0 | G6: =SUMIF(A24:A25,"OPEX",O24:O25) -> 0 | H6: =1-(G6/F6) -> #DIV/0! | AZ6: NRC | BA6: Unit | BB6: CAPEX | BC6: Hughes Equipment | BD6: VSAT
A7: Number of Sites | C7: 1111 | F7: =SUM(F5:F6) -> 0 | G7: =SUM(G5:G6) -> 0 | H7: =1-(G7/F7) -> #DIV/0! | AZ7: MRC | BA7: Month | BB7: OPEX | BC7: Hughes Services | BD7: Managed Capacity Operations
A8: Remote Spares | C8: 0 | BA8: Year | BC8: 3rd Party Equipment | BD8: Ka- Band Managed Capacity
A9: Total of Spares | C9: 0 | BA9: Mbps | BC9: 3rd Party Services | BD9: Maintenace
A10: Service Plan | BA10: Kbps | BD10: Installation
A11: Total capacity SES-17 (Mbps) | C11: 0 | BA11: MB
B12: Overbooking | C12: 0
A13: Total Ka band Capacity (Mbps) | C13: 12323 | F13: Price x Site x Month | G13: Cost x Site x Month | H13: MARGIN | BA13: GB
A14: Average Mbps per Site | C14: 0 | F14: =F7/C7/C19 -> 0 | G14: =G7/C7/C19 -> 0 | H14: =1-(G14/F14) -> #DIV/0!
B15: #VALUE! | C15: 0
A16: Terminal Unit Price (USD) - ExWorks USA | C16: 0
A17: COST - SES Ka band Mbps / Month (USD) | C17: 0
A18: COST - HUGHES Ka band Mbps / Month (USD) | C18: 0
A19: Contract | C19: 11
A20: % sites with Penalties / month | C20: 0
A21: CAPEX Financing Rate | C21: 12
A22: UIT | C22: 0
A24: Type | B24: Category | C24: Subcategory | D24: Manufacturer Part # | E24: Product Code | F24: Description | G24: Qty | H24: Unit of Measure | I24: Discount | J24: Finance? | K24: Unit Price | L24: Unit Disc. Price | M24: Ext. Disc. Price | N24: Unit Cost | O24: Ext. Cost | P24: Profit Margin | Q24: Owner | R24: Monthly Price per Site | S24: Monthly Cost per Site | T24: Monthly Price per Mbps | U24: Monthly Cost per Mbps | V24: Financed CAPEX | W24: Financed Monthly Price per Site | X24: Notes
A25: 1111 | D25: qqqqq+qqq | F25: 11 | G25: 22 | I25: 11 | J25: www | K25: =Table1[[#This Row],[Unit Cost]]/0.7 -> 121.54286 | L25: =Table1[[#This Row],[Unit Price]]*(1-Table1[[#This Row],[Discount]]) -> -1215.4286 | M25: =IF(Table1[[#This Row],[Type]]="OPEX",$C$19,1)*Table1[[#This Row],[Unit Disc. Price]]*Table1[[#This Row],[Qty]] -> -26739.429 | N25: 85.08 | O25: =IF(Table1[[#This Row],[Type]]="OPEX",$C$19,1)*Table1[[#This Row],[Unit Cost]]*Table1[[#This Row],[Qty]] -> 1871.76 | P25: =1-(Table1[[#This Row],[Ext. Cost]]/Table1[[#This Row],[Ext. Disc. Price]]) -> 1.07 | Q25: HNS | R25: =Table1[[#This Row],[Ext. Disc. Price]]/$C$7/$C$19 -> -2.1879902 | S25: =Table1[[#This Row],[Ext. Cost]]/$C$7/$C$19 -> 0.15315932 | T25: =Table1[[#This Row],[Ext. Disc. Price]]/$C$13/$C$19 -> -0.1972618 | U25: =Table1[[#This Row],[Ext. Cost]]/$C$13/$C$19 -> 0.013808326 | V25: =IF(AND(Table1[[#This Row],[Type]]="CAPEX",Table1[[#This Row],[Finance?]]="MRC"),PMT($C$21/12,$C$19,-Table1[[#This Row],[Ext. Disc. Price]]),0) -> 0 | W25: =IF(AND(Table1[[#This Row],[Type]]="CAPEX",Table1[[#This Row],[Finance?]]="MRC"),PMT($C$21/12,$C$19,-Table1[[#This Row],[Ext. Disc. Price]])/$C$7,IF(Table1[[#This Row],[Type]]="OPEX",Table1[[#This Row],[Ext. Disc. Price]]/$C$7/$C$19,0)) -> 0

Sheet Margin Analysis
B2: Number of Sites | C2: ='QTO DB'!C7 -> 1111
B3: Total Mbps | C3: ='QTO DB'!C13 -> 12323
B4: Contract Term | C4: ='QTO DB'!C19 -> 11
B7: MARGIN ANALYSIS SUMMARY
C12: Disct. Ext. Price | D12: Ext. Cost. | E12: % of Project | F12: Monthly Price / Site | G12: Monthly Cost / Site | H12: Monthly Price / Mbps | I12: Monthly Cost / Mbps | J12: Margin
B13: Total general | C13: 0 | D13: 0 | E13: #DIV/0! | J13: #DIV/0!

Sheet Customer View
A1: QUOTE
E2: Quote #: | F2: QTO_000XXXX-00
E3: Date: | F3: =TODAY() -> 45862
E5: DO NOT DISTRIBUTE
A8: Prepared For: | B8: ='QTO DB'!$C$2 | D8: Prepared By: | E8: ='QTO DB'!$C$4
A11: Monthly Recurring Payment per Site
C12: Finance? | D12: www
A14: Service | B14: Sites | C14: Monthly Price per Site
A15: Unlimited Satellite Internet Service (Includes 74cm ant.,2W Radio and HT2000W IDU) | B15: ='QTO DB'!C7 -> 1111 | C15: 0
A17: One Time Payment
A18: Finance? | B18: (Varios elementos)
A20: Item | B20: Qty | C20: Unit Price | D20: Discount | E20: Unit Disc. Price | F20: Ext. Disc. Price
A21: Total general
A54: 4)
A55: 5)
A56: 6)
A57: 7)
A58: 8)
A59: 9)
A60: 10)
A61: 11)
A62: 12)

Sheet FIELD SERVICES
A1: Item | B1: Servicios | C1: Costo (USD) | D1: Precio (USD) | E1: Pais | F1: Zona | G1: Tipo de Servicios
A2: 1 | B2: Instalación servicio de internet con VSAT: 90cm /2W/ HT2010 /HT2010W equipo refurbish o nuevo | C2: 120 | D2: 240 | E2: PERU | F2: BASICA | G2: Internet
A3: 2 | B3: Instalación servicio de internet con VSAT: 90cm /2W/ HT2010 /HT2010W equipo refurbish o nuevo | C3: 165 | D3: 330 | E3: PERU | F3: INTERMEDIA | G3: Internet
A4: 3 | B4: Instalación servicio de internet con VSAT: 90cm /2W/ HT2010 /HT2010W equipo refurbish o nuevo | C4: 210 | D4: 420 | E4: PERU | F4: CRITICA | G4: Internet
A5: 4 | B5: Instalación servicio de internet con VSAT: 90cm /2W/ HT2010 /HT2010W equipo refurbish o nuevo | C5: 330 | D5: 660 | E5: PERU | F5: EXTREMO | G5: Internet
A6: 5 | B6: Instalación servicio de internet con VSAT: 120cm /3W/ HT2010 /HT2010W equipo refurbish o nuevo | C6: 140 | D6: 280 | E6: PERU | F6: BASICA | G6: Internet o CBoS
A7: 6 | B7: Instalación servicio de internet con VSAT: 120cm /3W/ HT2010 /HT2010W equipo refurbish o nuevo | C7: 185 | D7: 370 | E7: PERU | F7: INTERMEDIA | G7: Internet o CBoS
A8: 7 | B8: Instalación servicio de internet con VSAT: 120cm /3W/ HT2010 /HT2010W equipo refurbish o nuevo | C8: 230 | D8: 460 | E8: PERU | F8: CRITICA | G8: Internet o CBoS
A9: 8 | B9: Instalación servicio de internet con VSAT: 120cm /3W/ HT2010 /HT2010W equipo refurbish o nuevo | C9: 350 | D9: 700 | E9: PERU | F9: EXTREMO | G9: Internet o CBoS
A10: 9 | B10: Instalación servicio de CBoS con VSAT: 120cm /3W/ HT2524 equipo nuevo | C10: 140 | D10: 280 | E10: PERU | F10: BASICA | G10: CBoS
A11: 10 | B11: Instalación servicio de CBoS con VSAT: 120cm /3W/ HT2524 equipo nuevo | C11: 185 | D11: 370 | E11: PERU | F11: INTERMEDIA | G11: CBoS
A12: 11 | B12: Instalación servicio de CBoS con VSAT: 120cm /3W/ HT2524 equipo nuevo | C12: 230 | D12: 460 | E12: PERU | F12: CRITICA | G12: CBoS
A13: 12 | B13: Instalación servicio de CBoS con VSAT: 120cm /3W/ HT2524 equipo nuevo | C13: 350 | D13: 700 | E13: PERU | F13: EXTREMO | G13: CBoS
A14: 13 | B14: Paneles solares Autonomía : 8 Horas Potencia de Carga : VSAT + AP + CPE = 170W Numero de paneles: 2 Paneles Inversor 600W Controlador de Panel Solar 20A Bateria 100 ah Kit de Cables y Conectores | C14: 426 | D14: 608 | E14: PERU
A15: 14 | B15: Montaje de tablero de energía; instalación de controlador solar, cargador de baterías, baterías e inversor | C15: 40 | D15: =C15/0.7 -> 57.142857 | E15: PERU
A16: 15 | B16: Mantenimiento Correctivo 8x5 x mes | C16: 289.47368 | D16: =C16/0.7 -> 413.53383 | E16: PERU | G16: Internet
A17: 16 | B17: Mantenimiento Correctivo 24x7 x mes | C17: 657.89474 | D17: =C17/0.7 -> 939.84962 | E17: PERU | G17: Internet
A18: 17 | B18: Mantenimiento Correctivo x Evento | C18: 57.894737 | D18: =C18/0.7 -> 82.706767 | E18: PERU | G18: Internet
A19: 18 | B19: Mantenimiento Preventivo x Evento | C19: 57.894737 | D19: =C19/0.7 -> 82.706767 | E19: PERU | G19: Internet
A20: 19 | B20: Obra Civil con base de concreto - antena 90cm | C20: 65.789474 | D20: =C20/0.7 -> 93.984962 | E20: PERU | G20: Internet
A21: 20 | B21: Obra Civil con base de concreto - antena 120cm | C21: 78.947368 | D21: =C21/0.7 -> 112.78195 | E21: PERU | G21: Internet
A22: 21 | B22: Implementacion de Pozo a Tierra - 10 ohm | C22: 210.52632 | D22: =C22/0.7 -> 300.75188 | E22: PERU | G22: Internet
A23: 25 | B23: Instalacion Basica Access Point Indoor | C23: 31.578947 | D23: =C23/0.7 -> 45.112782 | E23: PERU | G23: Internet
A24: 26 | B24: Instalacion Basica Access Point Outdoor | C24: 39.473684 | D24: =C24/0.7 -> 56.390977 | E24: PERU | G24: Internet
A25: 27 | B25: Instalacion y Configuracion Router CPE Mikrotik | C25: 31.578947 | D25: =C25/0.7 -> 45.112782 | E25: PERU | G25: Internet
A26: 28 | B26: Cableado Estructurado UTP CAT6/6A 30 mts | C26: 27.631579 | D26: =C26/0.7 -> 39.473684 | E26: PERU | G26: Internet
A27: 29 | B27: Cableado Estructurado CAT6/6A 60 mts | C27: 55.263158 | D27: =C27/0.7 -> 78.947368 | E27: PERU | G27: Internet
... A29: 31 | B29: Montaje de panel informativo - Zona WiFi - Digital | C29: 10 | D29: =C29/0.7 -> 14.285714 | E29: PERU | G29: Internet

Sheet ZONAS PERU
A1: Departamento | B1: Provincia | C1: Distrito | D1: Nivel
A2: AMAZONAS | B2: CHACHAPOYAS | C2: Todos | D2: Básica
A3: AMAZONAS | B3: BAGUA | C3: Todos | D3: Básica
A4: AMAZONAS | B4: LUYA | C4: Todos | D4: Básica
A5: AMAZONAS | B5: BONGARA | C5: Todos | D5: Básica
A6: AMAZONAS | B6: CONDORCANQUI | C6: Todos | D6: Critica
A7: AMAZONAS | B7: RODRIGUEZ DE MENDOZA | C7: Todos | D7: Intermedia
A8: AMAZONAS | B8: UTCUBAMBA | C8: Todos | D8: Básica
A9: ANCASH | B9: HUARAZ | C9: Todos | D9: Básica
A10: ANCASH | B10: AIJA | C10: Todos | D10: Básica
A11: ANCASH | B11: ANTONIO RAYMONDI | C11: Todos | D11: Intermedia
A12: ANCASH | B12: ASUNCION | C12: Todos | D12: Intermedia
... A190: SAN MARTIN | B190: HUALLAGA | C190: ALTO SAPOSOA | D190: Extremo

Sheet Resumen
B2: Count of Hughes ID | C2: Column Labels
B3: Row Labels | C3: Monee, IL | D3: North Platte, NE | E3: Riverside, CA | F3: Spokane, WA | G3: Grand Total
B4: U019 | C4: 4 | G4: 4
B5: U020 | D5: 6 | G5: 6
B6: U021 | E6: 1 | G6: 1
B7: U023 | F7: 4 | G7: 4
B8: U025 | C8: 4 | G8: 4
B9: U026 | C9: 4 | G9: 4
B10: U027 | C10: 4 | G10: 4
B11: Grand Total | C11: 16 | D11: 6 | E11: 1 | F11: 4 | G11: 27
B13: Count of Hughes ID | C13: Column Labels
B14: Row Labels | C14: OFFNET | D14: Grand Total
B15: OFFNET | C15: 1 | D15: 1
B16: Grand Total | C16: 1 | D16: 1

Sheet QTO Unlimited Service Plans
B3: LATAM SERVICE PLANS
B4: UNLIMTED SERVICE PLANS | S4: HUGHES Unlimited Service Plan´s Pricing
B5: Service Plan | C5: MIR | E5: CIR | S5: 12 | T5: % | U5: 24 | V5: % | W5: 36 | X5: %
C6: Download (Mbps) | D6: Upload (Mbps) | E6: Download (Mbps) | F6: Upload (Mbps) | G6: Total CIR | H6: SLA | I6: Cost per Mbps Ka Band T19 | J6: Operations Cost per Site | K6: Internet Cost per Mbps | L6: Total Cost | M6: Target Price | N6: Margin | O6: Price / MBPS | Q6: Markup | R6: Price MRC | S6: MRC Price | T6: Markup | U6: MRC Price | V6: Markup | W6: MRC Price | X6: Markup | AA6: Target Price for TGS
B7: 1 | C7: 5 | D7: 1 | E7: =C7*10% -> 0.5 | F7: =D7*10% -> 0.1 | G7: 1 | H7: 1 | I7: 41.551084 | J7: 9.6098515 | K7: 3.5183333 | L7: =(I7+K7)*G7+J7 -> 54.679268 | M7: 70 | N7: =(M7-L7)/M7 -> 0.21886759 | O7: =+M7/G7 -> 70 | Q7: 0.4 | R7: =L7/(1-Q7) -> 91.132114 | S7: =L7/(1-T7) -> 91.132114 | T7: 0.4 | U7: =L7/(1-V7) -> 84.121951 | V7: 0.35 | W7: =L7/(1-X7) -> 78.113241 | X7: 0.3
B8: 2 | C8: 10 | D8: 2 | E8: =C8*10% -> 1 | F8: =D8*10% -> 0.2 | G8: =E8+F8 -> 1.2 | H8: 1 | I8: 41.551084 | J8: =+J7 -> 9.6098515 | K8: 3.5183333 | L8: =(I8+K8)*G8+J8 -> 63.693152 | M8: 120 | N8: =(M8-L8)/M8 -> 0.46922373 | O8: =+M8/G8 -> 100 | Q8: 0.4 | R8: =L8/(1-Q8) -> 106.15525 | S8: =L8/(1-T8) -> 106.15525 | T8: 0.4 | U8: =L8/(1-V8) -> 97.989464 | V8: 0.35 | W8: =L8/(1-X8) -> 90.990217 | X8: 0.3
B9: 3 | C9: 15 | D9: 3 | E9: =C9*10% -> 1.5 | F9: =D9*10% -> 0.3 | G9: =E9+F9 -> 1.8 | H9: 1 | I9: 41.551084 | J9: =+J7 -> 9.6098515 | K9: 3.5183333 | L9: =(I9+K9)*G9+J9 -> 90.734802 | M9: 170 | N9: =(M9-L9)/M9 -> 0.46626587 | O9: =+M9/G9 -> 94.444444 | Q9: 0.4 | R9: =L9/(1-Q9) -> 151.22467 | S9: =L9/(1-T9) -> 151.22467 | T9: 0.4 | U9: =L9/(1-V9) -> 139.592 | V9: 0.35 | W9: =L9/(1-X9) -> 129.62115 | X9: 0.3
B12: BACKUP PLAN | S12: HUGHES Unlimited Service Plan´s Pricing
B13: Service Plan | C13: MIR | E13: Monthly Allowance | S13: 12 | T13: % | U13: 24 | V13: % | W13: 36 | X13: %
C14: Download (Mbps) | D14: Upload (Mbps) | E14: GB/Month | H14: SLA | I14: Total CIR | J14: Operations Cost per Mbps | K14: Internet Cost per Mbps | L14: Total Cost | M14: Target Price | N14: Margin | Q14: Markup | R14: Price MRC | S14: MRC Price | T14: Markup | U14: MRC Price | V14: Markup | W14: MRC Price | X14: Markup
B15: 4 | C15: 50 | D15: 5 | E15: 2 | H15: 1 | I15: =0.006 -> 0.006 | J15: =+$J$7 -> 9.6098515 | K15: 3.5183333 | L15: =(I15+K15)*G15+J15 -> 9.6098515 | M15: 20 | N15: =(M15-L15)/M15 -> 0.51950742 | Q15: 0.4 | R15: =(E15*H15*L15)/(1-Q15) -> 32.032838 | S15: 20 | U15: 18 | W15: 16
B16: 4 | C16: 10 | D16: 1 | E16: 1 | H16: 1 | I16: =0.003 -> 0.003 | J16: =+$J$7 -> 9.6098515 | K16: 3.5183333 | L16: =(I16+K16)*G16+J16 -> 9.6098515 | M16: 20 | N16: =(M16-L16)/M16 -> 0.51950742 | P16: aquamanager
S17: Extra GB/Month
S18: 0.7
B21: UNLIMTED SERVICE PLANS for TGS | S21: HUGHES Unlimited Service Plan´s Pricing for TGS
B22: Service Plan | C22: MIR | E22: CIR | S22: 12 | T22: % | U22: 24 | V22: % | W22: 36 | X22: %
C23: Download (Mbps) | D23: Upload (Mbps) | E23: Download (Mbps) | F23: Upload (Mbps) | G23: Total CIR | H23: SLA | I23: Cost per Mbps Ka Band T19 | J23: Operations Cost per Mbps | K23: Internet Cost per Mbps | L23: Total Cost | M23: Target Price | N23: Margin | O23: Price / MBPS | Q23: Markup | R23: Price MRC | S23: Target price | T23: Markup | U23: MRC Price | V23: Markup | W23: MRC Price | X23: Markup
B24: 5 | C24: 5 | D24: 1 | E24: 0.5 | F24: 0.1 | G24: =E24+F24 -> 0.6 | H24: 1 | I24: 41.551084 | J24: =+$J$7 -> 9.6098515 | K24: 3.5183333 | L24: =(I24+J24+K24)*G24 -> 32.807561 | M24: 70 | N24: =(M24-L24)/M24 -> 0.53132056 | O24: =+M24/G24 -> 116.66667 | Q24: 0.4 | R24: =L24/(1-Q24) -> 54.679268 | S24: =L24/(1-T24) -> 54.679268 | T24: 0.4 | U24: =L24/(1-V24) -> 50.473171 | V24: =T24-5% -> 0.35 | W24: =L24/(1-X24) -> 46.867944 | X24: =V24-5% -> 0.3
B25: 6 | C25: 10 | D25: 3 | E25: 1 | F25: 0.3 | G25: =E25+F25 -> 1.3 | H25: 1 | I25: 41.551084 | J25: =+$J$7 -> 9.6098515 | K25: 3.5183333 | L25: =(I25+J25+K25)*G25 -> 71.083049 | M25: 130 | N25: =(M25-L25)/M25 -> 0.45320732 | O25: =+M25/G25 -> 100 | Q25: 0.4 | R25: =L25/(1-Q25) -> 118.47175 | S25: =L25/(1-T25) -> 118.47175 | T25: 0.4 | U25: =L25/(1-V25) -> 109.35854 | V25: =T25-5% -> 0.35 | W25: =L25/(1-X25) -> 101.54721 | X25: =V25-5% -> 0.3
B26: 7 | C26: 15 | D26: 3 | E26: 1.5 | F26: 0.3 | G26: =E26+F26 -> 1.8 | H26: 1 | I26: 41.551084 | J26: =+$J$7 -> 9.6098515 | K26: 3.5183333 | L26: =(I26+J26+K26)*G26 -> 98.422683 | M26: 170 | N26: =(M26-L26)/M26 -> 0.42104304 | O26: =+M26/G26 -> 94.444444 | Q26: 0.4 | R26: =L26/(1-Q26) -> 164.03781 | S26: =L26/(1-T26) -> 164.03781 | T26: 0.4 | U26: =L26/(1-V26) -> 151.41951 | V26: =T26-5% -> 0.35 | W26: =L26/(1-X26) -> 140.60383 | X26: =V26-5% -> 0.3
B27: 8 | C27: 20 | D27: 3 | E27: 2 | F27: 0.75 | G27: =E27+F27 -> 2.75 | H27: 1 | I27: 41.551084 | J27: =+$J$7 -> 9.6098515 | K27: 3.5183333 | L27: =(I27+J27+K27)*G27 -> 150.36799 | M27: 300 | N27: =(M27-L27)/M27 -> 0.49877337 | O27: =+M27/G27 -> 109.09091 | Q27: 0.4 | R27: =L27/(1-Q27) -> 250.61331 | S27: =L27/(1-T27) -> 250.61331 | T27: 0.4 | U27: =L27/(1-V27) -> 231.33537 | V27: =T27-5% -> 0.35 | W27: =L27/(1-X27) -> 214.81141 | X27: =V27-5% -> 0.3
B28: 9 | C28: 10 | D28: 1 | E28: 3 | F28: 1 | G28: =E28+F28 -> 4 | H28: 1 | I28: 41.551084 | J28: =+$J$7 -> 9.6098515 | K28: 3.5183333 | L28: =(I28+J28+K28)*G28 -> 218.71707 | M28: 465 | N28: =(M28-L28)/M28 -> 0.5296407 | O28: =+M28/G28 -> 116.25 | Q28: 0.4 | R28: =L28/(1-Q28) -> 364.52846 | S28: =L28/(1-T28) -> 364.52846 | T28: 0.4 | U28: =L28/(1-V28) -> 336.48781 | V28: =T28-5% -> 0.35 | W28: =L28/(1-X28) -> 312.45296 | X28: =V28-5% -> 0.3
B29: 10 | C29: 25 | D29: 3 | E29: 5 | F29: 1 | G29: =E29+F29 -> 6 | H29: 1 | I29: 41.551084 | J29: =+$J$7 -> 9.6098515 | K29: 3.5183333 | L29: =(I29+J29+K29)*G29 -> 328.07561 | M29: 925 | N29: =(M29-L29)/M29 -> 0.64532366 | O29: =+M29/G29 -> 154.16667 | Q29: 0.4 | R29: =L29/(1-Q29) -> 546.79268 | S29: =L29/(1-T29) -> 546.79268 | T29: 0.4 | U29: =L29/(1-V29) -> 504.73171 | V29: =T29-5% -> 0.35 | W29: =L29/(1-X29) -> 468.67944 | X29: =V29-5% -> 0.3
B30: 11 | C30: 50 | D30: 5 | E30: 15 | F30: 3 | G30: =E30+F30 -> 18 | H30: 1 | I30: 41.551084 | J30: =+$J$7 -> 9.6098515 | K30: 3.5183333 | L30: =(I30+J30+K30)*G30 -> 984.22683 | M30: 2350 | N30: =(M30-L30)/M30 -> 0.58118007 | O30: =+M30/G30 -> 130.55556 | Q30: 0.4 | R30: =L30/(1-Q30) -> 1640.3781 | S30: =L30/(1-T30) -> 1640.3781 | T30: 0.4 | U30: =L30/(1-V30) -> 1514.1951 | V30: =T30-5% -> 0.35 | W30: =L30/(1-X30) -> 1406.0383 | X30: =V30-5% -> 0.3
E31: =C30/E30 -> 3.3333333 | F31: =D30/F30 -> 1.6666667
K34: =I30+J30+K30 -> 54.679268

Sheet CashFlow-HUGHES PRIME
B1: ESTIMATED CASH FLOW - EPAD SATELITAL - ALL ITEMS - HUGHES AS A PRIME
J3: Without IVA
B4: PAYBACK | C4: =HLOOKUP(1,I13:AF14,2,0) -> #N/A | J4: TOTAL PRICE (USD) | K4: =#REF! -> #REF!
B5: NPV (12m) | C5: =NPV(C10,D37:O37)+C37 -> #REF! | J5: TOTAL PRICE (S/) | K5: =K4*#REF! -> #REF!
B6: NPV (24m) | C6: =NPV(C10,D37:AA37)+C37 -> #REF! | J6: FIRST PAYMENT | K6: 0
B7: NPV (36m) | C7: =NPV(C10,D37:AF37)+C37 -> #REF! | J7: MONTHLY PAYMENT | K7: =K4*4.17% -> #REF!
B8: NPV PROJECT (41m) | C8: =NPV(C10,D37:AF37)+C37 -> #REF!
B9: WACC (annual) | C9: 0.12
B10: WACC (Monthly) | C10: =+POWER(1+C9,1/12)-1 -> 0.0094887929
I13: =IF(I17>0,1,0) -> #REF! | J13: =IF(J17>0,1,0) -> #REF! | K13: =IF(K17>0,1,0) -> #REF! | L13: =IF(L17>0,1,0) -> #REF! | M13: =IF(M17>0,1,0) -> #REF! | N13: =IF(N17>0,1,0) -> #REF! | O13: =IF(O17>0,1,0) -> #REF! | P13: =IF(P17>0,1,0) -> #REF! | ... AF13: =IF(AF17>0,1,0) -> #REF!
C14: 0 | D14: 1 | E14: 2 | F14: 3 | G14: 4 | H14: 5 | I14: 6 | J14: 7 | K14: 8 | L14: 9 | M14: 10 | N14: 11 | O14: 12 | P14: 13 | Q14: 14 | R14: 15 | S14: 16 | T14: 17 | U14: 18 | V14: 19 | W14: 20 | X14: 21 | Y14: 22 | Z14: 23 | AA14: 24 | AB14: 25 | AC14: 26 | AD14: 27 | AE14: 28 | AF14: 29
C15: M0 | D15: M1 | E15: M2 | F15: M3 | G15: M4 | H15: M5 | I15: M6 | J15: M7 | K15: M8 | L15: M9 | M15: M10 | N15: M11 | O15: M12 | P15: M13 | Q15: M14 | R15: M15 | S15: M16 | T15: M17 | U15: M18 | V15: M19 | W15: M20 | X15: M21 | Y15: M22 | Z15: M23 | AA15: M24 | AB15: M25 | AC15: M26 | AD15: M27 | AE15: M28 | AF15: M29
C16: ROLL OUT
B17: CASH BALANCE | C17: =0+C20-C23-C31 -> #REF! | D17: =C17+D20-D23+D28-D31 -> #REF! | E17: =D17+E20-E23+E28-E31 -> #REF! | F17: =E17+F20-F23+F28-F31 -> #REF! | G17: =F17+G20-G23+G28-G31 -> #REF! | H17: =G17+H20-H23+H28-H31 -> #REF! | I17: =H17+I20-I23+I28-I31 -> #REF! | J17: =I17+J20-J23+J28-J31 -> #REF! | K17: =J17+K20-K23+K28-K31 -> #REF! | ... AF17: =AE17+AF20-AF23+AF28-AF31 -> #REF!
A19: OPEX | B19: OPERATING CASH FLOW
B20: INCOME | I20: =I21+I22 -> #REF! | J20: =J21+J22 -> #REF! | K20: =K21+K22 -> #REF! | L20: =L21+L22 -> #REF! | M20: =M21+M22 -> #REF! | N20: =N21+N22 -> #REF! | O20: =O21+O22 -> #REF! | P20: =P21+P22 -> #REF! | ... AF20: =AF21+AF22 -> #REF!
B21: PRONATEL First Payment | D21: 0 | E21: 0 | F21: 0 | G21: 0 | H21: 0 | I21: =K6 -> 0
B22: PRONATEL Monthly Payment | D22: 0 | E22: 0 | F22: 0 | G22: 0 | H22: 0 | I22: =$K$7 -> #REF! | J22: =$K$7 -> #REF! | K22: =$K$7 -> #REF! | L22: =$K$7 -> #REF! | M22: =$K$7 -> #REF! | N22: =$K$7 -> #REF! | O22: =$K$7 -> #REF! | P22: =$K$7 -> #REF! | ... AE22: =$K$7 -> #REF! | AF22: =K4*4.09% -> #REF!
B23: OUTFLOW | D23: =D24+D25+D26 -> 0 | E23: =E24+E25+E26 -> 0 | F23: =F24+F25+F26 -> 0 | G23: =G24+G25+G26 -> 0 | H23: =H24+H25+H26 -> 0 | I23: =I24+I25+I26 -> #REF! | J23: =J24+J25+J26 -> #REF! | K23: =K24+K25+K26 -> #REF! | ... AF23: =AF24+AF25+AF26 -> #REF!
B24: One Time Network and Management Operations | D24: 0 | E24: 0 | F24: 0 | G24: 0 | H24: 0 | I24: =#REF!/24 -> #REF! | J24: =$I$24 -> #REF! | K24: =$I$24 -> #REF! | L24: =$I$24 -> #REF! | M24: =$I$24 -> #REF! | N24: =$I$24 -> #REF! | O24: =$I$24 -> #REF! | P24: =$I$24 -> #REF! | Q24: =$I$24 -> #REF! | ... AF24: =$I$24 -> #REF!
B25: Recurring services - Management, call out | D25: 0 | E25: 0 | F25: 0 | G25: 0 | H25: 0 | I25: =#REF!/24 -> #REF! | J25: =$I$25 -> #REF! | K25: =$I$25 -> #REF! | L25: =$I$25 -> #REF! | M25: =$I$25 -> #REF! | N25: =$I$25 -> #REF! | O25: =$I$25 -> #REF! | P25: =$I$25 -> #REF! | Q25: =$I$25 -> #REF! | ... AF25: =$I$25 -> #REF!
B26: Space Segment Ka - T19V & SES-17 | D26: 0 | E26: 0 | F26: 0 | G26: 0 | H26: 0 | I26: =#REF!/24 -> #REF! | J26: =$I$26 -> #REF! | K26: =$I$26 -> #REF! | L26: =$I$26 -> #REF! | M26: =$I$26 -> #REF! | N26: =$I$26 -> #REF! | O26: =$I$26 -> #REF! | P26: =$I$26 -> #REF! | Q26: =$I$26 -> #REF! | ... AF26: =$I$26 -> #REF!
A27: CAPEX | B27: Penalties
B28: INCOME
C29: 0 | D29: 0 | E29: 0 | F29: 0 | G29: 0 | H29: 0 | I29: 0 | J29: 0 | K29: 0 | L29: 0 | M29: 0 | N29: 0 | O29: 0 | P29: 0 | Q29: 0 | R29: 0 | S29: 0 | T29: 0 | U29: 0 | V29: 0 | W29: 0 | X29: 0 | Y29: 0 | Z29: 0 | AA29: 0 | AB29: 0 | AC29: 0 | AD29: 0 | AE29: 0 | AF29: 0
C30: 0 | D30: 0 | E30: 0 | F30: 0 | G30: 0 | H30: 0 | I30: 0 | J30: 0 | K30: 0 | L30: 0 | M30: 0 | N30: 0 | O30: 0 | P30: 0 | Q30: 0 | R30: 0 | S30: 0 | T30: 0 | U30: 0 | V30: 0 | W30: 0 | X30: 0 | Y30: 0 | Z30: 0 | AA30: 0 | AB30: 0 | AC30: 0 | AD30: 0 | AE30: 0 | AF30: 0
B31: OUTFLOW | C31: =C32+C33+C34+C35+C36 -> #REF! | D31: =D32+D33+D34+D35+D36 -> #REF! | E31: =E32+E33+E34+E35+E36 -> #REF! | F31: =F32+F33+F34+F35+F36 -> #REF! | G31: =G32+G33+G34+G35+G36 -> #REF! | H31: =H32+H33+H34+H35+H36 -> #REF! | I31: =I32+I33+I34+I35+I36 -> 0 | J31: =J32+J33+J34+J35+J36 -> 0 | ... AF31: =AF32+AF33+AF34+AF35+AF36 -> 0
B32: Infraestructure | C32: =#REF! -> #REF! | D32: 0 | E32: 0 | F32: 0 | G32: 0 | H32: 0 | I32: 0 | J32: 0 | K32: 0 | L32: 0 | M32: 0 | N32: 0 | O32: 0 | P32: 0 | Q32: 0 | R32: 0 | S32: 0 | T32: 0 | U32: 0 | V32: 0 | W32: 0 | X32: 0 | Y32: 0 | Z32: 0 | AA32: 0 | AB32: 0 | AC32: 0 | AD32: 0 | AE32: 0 | AF32: 0
B33: One Time Services | C33: =#REF! -> #REF! | D33: 0 | E33: 0 | F33: 0 | G33: 0 | H33: 0 | I33: 0 | J33: 0 | K33: 0 | L33: 0 | M33: 0 | N33: 0 | O33: 0 | P33: 0 | Q33: 0 | R33: 0 | S33: 0 | T33: 0 | U33: 0 | V33: 0 | W33: 0 | X33: 0 | Y33: 0 | Z33: 0 | AA33: 0 | AB33: 0 | AC33: 0 | AD33: 0 | AE33: 0 | AF33: 0
B34: Installation + Site Survey + Materials Sites Ka Band | C34: 0 | D34: =#REF!/5 -> #REF! | E34: =#REF!/5 -> #REF! | F34: =#REF!/5 -> #REF! | G34: =#REF!/5 -> #REF! | H34: =#REF!/5 -> #REF! | I34: 0 | J34: 0 | K34: 0 | L34: 0 | M34: 0 | N34: 0 | O34: 0 | P34: 0 | Q34: 0 | R34: 0 | S34: 0 | T34: 0 | U34: 0 | V34: 0 | W34: 0 | X34: 0 | Y34: 0 | Z34: 0 | AA34: 0 | AB34: 0 | AC34: 0 | AD34: 0 | AE34: 0 | AF34: 0
B35: One Time Network and Management Operations | C35: =#REF! -> #REF! | D35: 0 | E35: 0 | F35: 0 | G35: 0 | H35: 0 | I35: 0 | J35: 0 | K35: 0 | L35: 0 | M35: 0 | N35: 0 | O35: 0 | P35: 0 | Q35: 0 | R35: 0 | S35: 0 | T35: 0 | U35: 0 | V35: 0 | W35: 0 | X35: 0 | Y35: 0 | Z35: 0 | AA35: 0 | AB35: 0 | AC35: 0 | AD35: 0 | AE35: 0 | AF35: 0
C36: 0 | D36: 0 | E36: 0 | F36: 0 | G36: 0 | H36: 0 | I36: 0 | J36: 0 | K36: 0 | L36: 0 | M36: 0 | N36: 0 | O36: 0 | P36: 0 | Q36: 0 | R36: 0 | S36: 0 | T36: 0 | U36: 0 | V36: 0 | W36: 0 | X36: 0 | Y36: 0 | Z36: 0 | AA36: 0 | AB36: 0 | AC36: 0 | AD36: 0 | AE36: 0 | AF36: 0
B37: FCF | C37: =C20-C23+C28-C31 -> #REF! | D37: =D20-D23+D28-D31 -> #REF! | E37: =E20-E23+E28-E31 -> #REF! | F37: =F20-F23+F28-F31 -> #REF! | G37: =G20-G23+G28-G31 -> #REF! | H37: =H20-H23+H28-H31 -> #REF! | I37: =I20-I23+I28-I31 -> #REF! | J37: =J20-J23+J28-J31 -> #REF! | ... AF37: =AF20-AF23+AF28-AF31 -> #REF!
B38: FCF Discounted | C38: =+C37*POWER(1+$C$10,-C14) -> #REF! | D38: =+D37*POWER(1+$C$10,-D14) -> #REF! | E38: =+E37*POWER(1+$C$10,-E14) -> #REF! | F38: =+F37*POWER(1+$C$10,-F14) -> #REF! | G38: =+G37*POWER(1+$C$10,-G14) -> #REF! | H38: =+H37*POWER(1+$C$10,-H14) -> #REF! | I38: =+I37*POWER(1+$C$10,-I14) -> #REF! | J38: =+J37*POWER(1+$C$10,-J14) -> #REF! | ... AF38: =+AF37*POWER(1+$C$10,-AF14) -> #REF!

Sheet QTO EPAD SELVA - ITEM 1
A1: QTO PRONATEL-EPAD SELVA - ITEM 1
A4: ITEM 3 | B4: Inputs | G4: PRICE | H4: COST | I4: MARGIN
B5: HUGHES T19 Number of Sites | C5: 388 | F5: CAPEX | G5: =SUMIF(A26:A175,"CAPEX",H26:H175) -> #REF! | H5: =SUMIF(A26:A175,"CAPEX",J26:J175) -> #REF! | I5: =1-(H5/G5) -> #REF!
B6: Sites out of coverage | C6: 0 | F6: OPEX | G6: =SUMIF(A26:A175,"OPEX",H26:H175) -> #REF! | H6: =SUMIF(A26:A175,"OPEX",J26:J175) -> #REF! | I6: =1-(H6/G6) -> #REF!
B7: Number of Sites | C7: =C5+C6 -> 388 | G7: =SUM(G5:G6) -> #REF! | H7: =SUM(H5:H6) -> #REF! | I7: =1-(H7/G7) -> #REF!
B8: Remote Spares | C8: 0.05
B9: Total of Spares
B10: Total capacity T19 (Mbps) | C10: 970
B11: Total capacity SES-17 (Mbps) | C11: 0
B12: Total Ka band Capacity (Mbps) | C12: =C10+C11 -> 970 | G12: Price x Site x Month | H12: Cost x Site x Month | I12: MARGIN
B13: Average Mbps per Site | C13: =C12/C7 -> 2.5 | G13: =G7/C7/C18 -> #REF! | H13: =H7/C7/C18 -> #REF! | I13: =1-(H13/G13) -> #REF!
B14: Tipo de Cambio | C14: 3.8
B15: Terminal Unit Price (USD) | C15: =G27+G28+G29+G33 -> 745.41429
B16: COST - SES Ka band Mbps / Month (USD) | C16: 155
B17: COST - HUGHES Ka band Mbps / Month (USD) | C17: 55
B18: Contract | C18: 24
B19: % sites with Penalties / month | C19: 0.01
B20: UIT | C20: =4950/C14 -> 1302.6316
A22: PRONATEL EPAD SELVA - ITEM 1
A24: INFRAESTRUCTURE
B25: CAPEX REMOTE TERMINALS - VSAT
B26: Manufacturer Part # | C26: Product Code | D26: Description | E26: Qty | F26: Unit of Pricing | G26: Unit Price | H26: Ext. Price | I26: Unit Cost | J26: Ext. Cost | K26: Profit Margin | L26: Owner
A27: CAPEX | B27: 1505216-0332 | C27: HT2010 | D27: HT2010 Consumer Broadband Satellite Router, Ka Band only | E27: =$C$7 -> 388 | F27: ea | G27: =I27/0.7 -> 109.71429 | H27: =E27*G27 -> 42569.143 | I27: 76.8 | J27: =E27*I27 -> 29798.4 | K27: =1-(J27/H27) -> 0.3 | L27: HNS | M27: VSAT
A28: CAPEX | B28: 1506307-0001+1506307-0101 | C28: AN-120-SG-P1 + AN-120-SG-P2 | D28: 1.2m Ka-Band antenna, Single IFL | E28: 0 | F28: ea | G28: =I28/0.7 -> 426.52857 | H28: =E28*G28 -> 0 | I28: 298.57 | J28: =E28*I28 -> 0 | K28: =1-(J28/H28) -> #DIV/0! | L28: HNS | M28: VSAT
A29: CAPEX | B29: 1506689-1004 | C29: HB220-L | D29: 3W Multi-mode radio, Ka-Band, RHCP | E29: =$C$7 -> 388 | F29: ea | G29: =I29/0.7 -> 138.45714 | H29: =E29*G29 -> 53721.371 | I29: 96.92 | J29: =E29*I29 -> 37604.96 | K29: =1-(J29/H29) -> 0.3 | L29: HNS | M29: VSAT
A30: CAPEX | B30: 1506560-0012+1506561-0011 | C30: AN-90-KA1-NL-4PK + AN-90-KA2-4PK | D30: 90cm Ka-Band antenna, Single IFL, 4 PK- 4 antennas | E30: 97 | F30: ea | G30: =I30/0.7 -> 410.3 | H30: =E30*G30 -> 39799.1 | I30: 287.21 | J30: =E30*I30 -> 27859.37 | K30: =1-(J30/H30) -> 0.3 | L30: HNS | M30: VSAT
A31: CAPEX | B31: 1506560-0022+ 1506561-0021 | C31: AN-90-KA1-NL-1PK + AN-90-KA2-1PK | D31: 90cm Ka-Band antenna, Single IFL, 1 PK | E31: 0 | F31: ea | G31: =I31/0.7 -> 129.4 | H31: =E31*G31 -> 0 | I31: 90.58 | J31: =E31*I31 -> 0 | K31: =1-(J31/H31) -> #DIV/0! | L31: HNS | M31: VSAT
A32: CAPEX | C32: Antenna Mast | D32: Trimast Mount for 74cm and 90cm antenna | E32: 388 | F32: ea | G32: =I32/0.7 -> 20 | H32: =E32*G32 -> 7760 | I32: 14 | J32: =E32*I32 -> 5432 | K32: =1-(J32/H32) -> 0.3 | L32: HNS | M32: VSAT
A33: CAPEX | B33: 611604104 | C33: Antenna Mast | D33: 1.2m Ka antenna tri-mast mount | E33: 0 | F33: ea | G33: =I33/0.7 -> 70.714286 | H33: =E33*G33 -> 0 | I33: 49.5 | J33: =E33*I33 -> 0 | K33: =1-(J33/H33) -> #DIV/0! | L33: HNS | M33: VSAT
H34: =SUM(H27:H33) -> 143849.61 | J34: =SUM(J27:J33) -> 100694.73 | K34: =1-(J34/H34) -> 0.3
D35: Discount | E35: 0 | H35: =-H34*E35 -> 0
H36: =H34+H35 -> 143849.61 | J36: =J34 -> 100694.73 | K36: =1-(J36/H36) -> 0.3
B38: CAPEX REMOTE TERMINALS - SPARE VSAT (20 kits vandalism and 5% for operations)
B39: Manufacturer Part # | C39: Product Code | D39: Description | E39: Qty | F39: Unit of Pricing | G39: Unit Price | H39: Ext. Price | I39: Unit Cost | J39: Ext. Cost | K39: Profit Margin | L39: Owner
A40: CAPEX | B40: 1505216-0332 | C40: HT2010 | D40: HT2010 Consumer Broadband Satellite Router, Ka Band only | E40: =ROUNDUP($C$8*$C$7,0) -> 20 | F40: ea | G40: =I40/0.7 -> 109.71429 | H40: =E40*G40 -> 2194.2857 | I40: 76.8 | J40: =E40*I40 -> 1536 | K40: =1-(J40/H40) -> 0.3 | L40: HNS | M40: VSAT
A41: CAPEX | B41: 1506307-0001+1506307-0101 | C41: AN-120-SG-P1 + AN-120-SG-P2 | D41: 1.2m Ka-Band antenna, Single IFL | E41: 0 | F41: ea | G41: =I41/0.7 -> 426.52857 | H41: =E41*G41 -> 0 | I41: 298.57 | J41: =E41*I41 -> 0 | K41: =1-(J41/H41) -> #DIV/0! | L41: HNS | M41: VSAT
A42: CAPEX | B42: 1506689-1004 | C42: HB220-L | D42: 3W Multi-mode radio, Ka-Band, RHCP | E42: =ROUNDUP($C$8*$C$7,0) -> 20 | F42: ea | G42: =I42/0.7 -> 138.45714 | H42: =E42*G42 -> 2769.1429 | I42: 96.92 | J42: =E42*I42 -> 1938.4 | K42: =1-(J42/H42) -> 0.3 | L42: HNS | M42: VSAT
A43: CAPEX | B43: 1506560-0012+1506561-0011 | C43: AN-90-KA1-NL-4PK + AN-90-KA2-4PK | D43: 90cm Ka-Band antenna, Single IFL, 4 PK- 4 antennas | E43: 5 | F43: ea | G43: =I43/0.7 -> 410.3 | H43: =E43*G43 -> 2051.5 | I43: 287.21 | J43: =E43*I43 -> 1436.05 | K43: =1-(J43/H43) -> 0.3 | L43: HNS | M43: VSAT
A44: CAPEX | B44: 1506560-0022+ 1506561-0021 | C44: AN-90-KA1-NL-1PK + AN-90-KA2-1PK | D44: 90cm Ka-Band antenna, Single IFL, 1 PK | E44: 0 | F44: ea | G44: =I44/0.7 -> 129.4 | H44: =E44*G44 -> 0 | I44: 90.58 | J44: =E44*I44 -> 0 | K44: =1-(J44/H44) -> #DIV/0! | L44: HNS | M44: VSAT
A45: CAPEX | C45: Antenna Mast | D45: Trimast Mount for 74cm and 90cm antenna | E45: 20 | F45: ea | G45: =I45/0.7 -> 20 | H45: =E45*G45 -> 400 | I45: 14 | J45: =E45*I45 -> 280 | K45: =1-(J45/H45) -> 0.3 | L45: HNS | M45: VSAT
A46: CAPEX | B46: 611604104 | C46: Antenna Mast | D46: 1.2m Ka antenna tri-mast mount | E46: 0 | F46: ea | G46: =I46/0.7 -> 70.714286 | H46: =E46*G46 -> 0 | I46: 49.5 | J46: =E46*I46 -> 0 | K46: =1-(J46/H46) -> #DIV/0! | L46: HNS | M46: VSAT
H47: =SUM(H40:H46) -> 7414.9286 | J47: =SUM(J40:J46) -> 5190.45 | K47: =1-(J47/H47) -> 0.3
D48: Discount | E48: 0 | H48: =-H47*E48 -> 0
H49: =H47+H48 -> 7414.9286 | J49: =J47 -> 5190.45 | K49: =1-(J49/H49) -> 0.3
B50: SOLAR PANELS
B51: Vendor | C51: Product Code | D51: Description | E51: Qty | F51: Unit of Pricing | G51: Unit Price | H51: Ext. Price | I51: Unit Cost | J51: Ext. Cost | K51: Profit Margin | L51: Owner
A52: CAPEX | D52: Solar Panel | E52: =C7 -> 388 | F52: ea | G52: =I52/0.75 -> #REF! | H52: =E52*G52 -> #REF! | I52: =#REF!+#REF! -> #REF! | J52: =E52*I52 -> #REF! | K52: =1-(J52/H52) -> #REF! | L52: HDP
A53: CAPEX | E53: =ROUNDUP($C$8*$C$7,0) -> 20 | F53: ea | G53: =I53/0.75 -> #REF! | H53: =E53*G53 -> #REF! | I53: =#REF!+#REF! -> #REF! | J53: =E53*I53 -> #REF! | K53: =1-(J53/H53) -> #REF! | L53: HDP
H54: =SUM(H50:H53) -> #REF! | J54: =SUM(J50:J53) -> #REF! | K54: =1-(J54/H54) -> #REF!
D55: Discount | E55: 0 | H55: =-H54*E55 -> #REF!
H56: =H54+H55 -> #REF! | J56: =J54 -> #REF! | K56: =1-(J56/H56) -> #REF!
B58: CABINETS
B59: Vendor | C59: Product Code | D59: Description | E59: Qty | F59: Unit of Pricing | G59: Unit Price | H59: Ext. Price | I59: Unit Cost | J59: Ext. Cost | K59: Profit Margin | L59: Owner
A60: CAPEX | D60: Cabinet Outdoor | E60: =$C$7 -> 388 | F60: ea | G60: =I60/0.75 -> #REF! | H60: =E60*G60 -> #REF! | I60: =#REF! -> #REF! | J60: =E60*I60 -> #REF! | K60: =1-(J60/H60) -> #REF! | L60: HDP
A61: CAPEX | E61: =ROUNDUP($C$8*$C$7,0) -> 20 | F61: ea | G61: =I61/0.75 -> #REF! | H61: =E61*G61 -> #REF! | I61: =#REF! -> #REF! | J61: =E61*I61 -> #REF! | K61: =1-(J61/H61) -> #REF! | L61: HDP
H62: =SUM(H58:H61) -> #REF! | J62: =SUM(J58:J61) -> #REF! | K62: =1-(J62/H62) -> #REF!
D63: Discount | E63: 0 | H63: =-H62*E63 -> #REF!
H64: =H62+H63 -> #REF! | J64: =J62 -> #REF! | K64: =1-(J64/H64) -> #REF!
B66: ROUTERS MIKROTIK
B67: Vendor | C67: Product Code | D67: Description | E67: Qty | F67: Unit of Pricing | G67: Unit Price | H67: Ext. Price | I67: Unit Cost | J67: Ext. Cost | K67: Profit Margin | L67: Owner
A68: CAPEX | B68: MIKROTIK | C68: RB760IGS | D68: 5x Gigabit Ethernet, SFP, Dual Core 880MHz CPU, 256MB RAM, USB, microSD, RouterOS L4, IPsec hardware encryption support and The Dude server package | E68: =$C$7 -> 388 | F68: ea | G68: =I68/0.75 -> #REF! | H68: =E68*G68 -> #REF! | I68: =#REF! -> #REF! | J68: =E68*I68 -> #REF! | K68: =1-(J68/H68) -> #REF! | L68: HDP
A69: CAPEX | B69: MIKROTIK | C69: RB760IGS | D69: 5x Gigabit Ethernet, SFP, Dual Core 880MHz CPU, 256MB RAM, USB, microSD, RouterOS L4, IPsec hardware encryption support and The Dude server package (20 kits vandalism and 5% for operations) | E69: =ROUNDUP($C$8*$C$7,0) -> 20 | F69: ea | G69: =I69/0.75 -> #REF! | H69: =E69*G69 -> #REF! | I69: =#REF! -> #REF! | J69: =E69*I69 -> #REF! | K69: =1-(J69/H69) -> #REF! | L69: HDP
H70: =SUM(H66:H69) -> #REF! | J70: =SUM(J66:J69) -> #REF! | K70: =1-(J70/H70) -> #REF!
D71: Discount | E71: 0 | H71: =-H70*E71 -> #REF!
H72: =H70+H71 -> #REF! | J72: =J70 -> #REF! | K72: =1-(J72/H72) -> #REF!
B74: DESKTOP COMPUTER
B75: Vendor | C75: Product Code | D75: Description | E75: Qty | F75: Unit of Pricing | G75: Unit Price | H75: Ext. Price | I75: Unit Cost | J75: Ext. Cost | K75: Profit Margin | L75: Owner
A76: CAPEX | D76: Computadora para Monitoreo | E76: 1 | F76: ea | G76: =I76/0.75 -> 6666.6667 | H76: =E76*G76 -> 6666.6667 | I76: 5000 | J76: =E76*I76 -> 5000 | K76: =1-(J76/H76) -> 0.25 | L76: HDP
H77: =SUM(H74:H76) -> 6666.6667 | J77: =SUM(J74:J76) -> 5000 | K77: =1-(J77/H77) -> 0.25
D78: Discount | E78: 0 | H78: =-H77*E78 -> 0
H79: =H77+H78 -> 6666.6667 | J79: =J77 -> 5000 | K79: =1-(J79/H79) -> 0.25
B81: IBOSS-WEB FILTERING SOLUTION
B82: Vendor | C82: Product Code | D82: Description | E82: Qty | F82: Unit of Pricing | G82: Unit Price | H82: Ext. Price | I82: Unit Cost | J82: Ext. Cost | K82: Profit Margin | L82: Owner
A83: CAPEX | D83: FORTINET ITEM 1 | E83: 1 | F83: ea | G83: =I83/0.75 -> #REF! | H83: =E83*G83 -> #REF! | I83: =#REF! -> #REF! | J83: =E83*I83 -> #REF! | K83: =1-(J83/H83) -> #REF! | L83: HDP
A84: CAPEX | D84: FORTINET ITEM 2 | E84: 0 | F84: ea | G84: =I84/0.75 -> 0 | H84: =E84*G84*$C$18 -> 0 | I84: 0 | J84: =E84*I84*$C$18 -> 0 | K84: =1-(J84/H84) -> #DIV/0! | L84: HDP
A85: CAPEX | D85: FORTINET ITEM 3 | E85: 0 | F85: ea | G85: =I85/0.75 -> 0 | H85: =E85*G85*$C$18 -> 0 | I85: 0 | J85: =E85*I85*$C$18 -> 0 | K85: =1-(J85/H85) -> #DIV/0! | L85: HDP
A86: CAPEX | D86: FORTINET ITEM 4 | E86: 0 | F86: ea | G86: =I86/0.75 -> 0 | H86: =E86*G86*$C$18 -> 0 | I86: 0 | J86: =E86*I86*$C$18 -> 0 | K86: =1-(J86/H86) -> #DIV/0! | L86: HDP
A87: CAPEX | D87: FORTINET ITEM 5 | E87: 0 | F87: ea | G87: =I87/0.75 -> 0 | H87: =E87*G87*$C$18 -> 0 | I87: 0 | J87: =E87*I87*$C$18 -> 0 | K87: =1-(J87/H87) -> #DIV/0! | L87: HDP
A88: CAPEX | D88: FORTINET ALL ITEMS | E88: 0 | F88: ea | G88: =I88/0.75 -> 0 | H88: =E88*G88 -> 0 | I88: 0 | J88: =E88*I88 -> 0 | K88: =1-(J88/H88) -> #DIV/0! | L88: HDP
A89: CAPEX | F89: ea | G89: =I89/0.75 -> 0 | H89: =E89*G89 -> 0 | J89: =E89*I89 -> 0 | K89: =1-(J89/H89) -> #DIV/0! | L89: HDP
A90: CAPEX | F90: ea | G90: =I90/0.75 -> 0 | H90: =E90*G90 -> 0 | J90: =E90*I90 -> 0 | K90: =1-(J90/H90) -> #DIV/0! | L90: HDP
A91: CAPEX | F91: ea | G91: =I91/0.75 -> 0 | H91: =E91*G91 -> 0 | J91: =E91*I91 -> 0 | K91: =1-(J91/H91) -> #DIV/0! | L91: HDP
F92: ea | G92: =I92/0.6 -> 0 | H92: =E92*G92 -> 0 | I92: 0 | J92: =E92*I92 -> 0 | K92: =1-(J92/H92) -> #DIV/0! | L92: HDP
H93: =SUM(H83:H92) -> #REF! | J93: =SUM(J83:J92) -> #REF! | K93: =1-(J93/H93) -> #REF!
D94: Discount | E94: 0 | H94: =-H93*E94 -> #REF!
H95: =H93+H94 -> #REF! | J95: =J93 -> #REF! | K95: =1-(J95/H95) -> #REF!
B96: ACCESS POINTS
B97: Vendor | C97: Product Code | D97: Description | E97: Qty | F97: Unit of Pricing | G97: Unit Price | H97: Ext. Price | I97: Unit Cost | J97: Ext. Cost | K97: Profit Margin | L97: Owner
A98: CAPEX | B98: CAMBIUM | D98: Outdoor Dual radio WiFi 6 AP Omni 2x2, GbE. RW | E98: =C7*2 -> 776 | F98: ea | G98: =I98/0.75 -> #REF! | H98: =E98*G98 -> #REF! | I98: =#REF! -> #REF! | J98: =E98*I98 -> #REF! | K98: =1-(J98/H98) -> #REF! | L98: HDP
A99: CAPEX | B99: CAMBIUM | D99: PoE, 60W, 56V, 5GbE DC Injector, Indoor, Energy Level 6 Supply, accepts C5 connector | E99: =C7*2 -> 776 | F99: ea | G99: =I99/0.75 -> #REF! | H99: =E99*G99 -> #REF! | I99: =#REF! -> #REF! | J99: =E99*I99 -> #REF! | K99: =1-(J99/H99) -> #REF! | L99: HDP
A100: CAPEX | B100: CAMBIUM | D100: AC line cord, US Type B, 720mm, C5 connector | E100: =C7*2 -> 776 | F100: ea | G100: =I100/0.75 -> #REF! | H100: =E100*G100 -> #REF! | I100: =#REF! -> #REF! | J100: =E100*I100 -> #REF! | K100: =1-(J100/H100) -> #REF! | L100: HDP
A101: CAPEX | B101: CAMBIUM | D101: XMS-Cloud 3-year subscription for Education: 2 and 3-radio AP with all EasyPass modules and Cambium Care Advanced Support | E101: =C7*2 -> 776 | F101: ea | G101: =I101/0.75 -> #REF! | H101: =E101*G101 -> #REF! | I101: =#REF! -> #REF! | J101: =E101*I101 -> #REF! | K101: =1-(J101/H101) -> #REF! | L101: HDP
A102: CAPEX | B102: CAMBIUM | D102: Outdoor Dual radio WiFi 6 AP Omni 2x2, GbE. RW | E102: =ROUNDUP($C$8*$C$7,0)*2 -> 40 | F102: ea | G102: =I102/0.75 -> #REF! | H102: =E102*G102 -> #REF! | I102: =#REF! -> #REF! | J102: =E102*I102 -> #REF! | K102: =1-(J102/H102) -> #REF! | L102: HDP
A103: CAPEX | B103: CAMBIUM | D103: PoE, 60W, 56V, 5GbE DC Injector, Indoor, Energy Level 6 Supply, accepts C5 connector | E103: =ROUNDUP($C$8*$C$7,0)*2 -> 40 | F103: ea | G103: =I103/0.75 -> #REF! | H103: =E103*G103 -> #REF! | I103: =#REF! -> #REF! | J103: =E103*I103 -> #REF! | K103: =1-(J103/H103) -> #REF! | L103: HDP
A104: CAPEX | B104: CAMBIUM | D104: AC line cord, US Type B, 720mm, C5 connector | E104: =ROUNDUP($C$8*$C$7,0)*2 -> 40 | F104: ea | G104: =I104/0.75 -> #REF! | H104: =E104*G104 -> #REF! | I104: =#REF! -> #REF! | J104: =E104*I104 -> #REF! | K104: =1-(J104/H104) -> #REF! | L104: HDP
E105: 0 | F105: ea | G105: =I105/0.75 -> 0 | H105: =E105*G105 -> 0 | I105: 0 | J105: =E105*I105 -> 0 | K105: =1-(J105/H105) -> #DIV/0! | L105: HDP
E106: 0 | F106: ea | G106: =I106/0.75 -> 0 | H106: =E106*G106 -> 0 | I106: 0 | J106: =E106*I106 -> 0 | K106: =1-(J106/H106) -> #DIV/0! | L106: HDP
E107: 0 | F107: ea | G107: =I107/0.75 -> 0 | H107: =E107*G107 -> 0 | I107: 0 | J107: =E107*I107 -> 0 | K107: =1-(J107/H107) -> #DIV/0! | L107: HDP
F108: ea | G108: =I108/0.6 -> 0 | H108: =E108*G108 -> 0 | I108: 0 | J108: =E108*I108 -> 0 | K108: =1-(J108/H108) -> #DIV/0! | L108: HDP
H109: =SUM(H98:H108) -> #REF! | J109: =SUM(J98:J108) -> #REF! | K109: =1-(J109/H109) -> #REF!
...

Sheet QTO EPAD SELVA - ITEM 2
A1: QTO PRONATEL-EPAD SELVA - ITEM 2
A4: ITEM 3 | B4: Inputs | G4: PRICE | H4: COST | I4: MARGIN
B5: HUGHES T19 Number of Sites | C5: 270 | F5: CAPEX | G5: =SUMIF(A26:A175,"CAPEX",H26:H175) -> #REF! | H5: =SUMIF(A26:A175,"CAPEX",J26:J175) -> #REF! | I5: =1-(H5/G5) -> #REF!
B6: Sites out of coverage | C6: 0 | F6: OPEX | G6: =SUMIF(A26:A175,"OPEX",H26:H175) -> #REF! | H6: =SUMIF(A26:A175,"OPEX",J26:J175) -> #REF! | I6: =1-(H6/G6) -> #REF!
B7: Number of Sites | C7: =C5+C6 -> 270 | G7: =SUM(G5:G6) -> #REF! | H7: =SUM(H5:H6) -> #REF! | I7: =1-(H7/G7) -> #REF!
B8: Remote Spares | C8: 0.05
B9: Total of Spares
B10: Total capacity T19 (Mbps) | C10: 675
B11: Total capacity SES-17 (Mbps) | C11: 0
B12: Total Ka band Capacity (Mbps) | C12: =C10+C11 -> 675 | G12: Price x Site x Month | H12: Cost x Site x Month | I12: MARGIN
B13: Average Mbps per Site | C13: =C12/C7 -> 2.5 | G13: =G7/C7/C18 -> #REF! | H13: =H7/C7/C18 -> #REF! | I13: =1-(H13/G13) -> #REF!
B14: Tipo de Cambio | C14: 3.8
B15: Terminal Unit Price (USD) | C15: =G27+G28+G29+G33 -> 745.41429
B16: COST - SES Ka band Mbps / Month (USD) | C16: 155
B17: COST - HUGHES Ka band Mbps / Month (USD) | C17: 55
B18: Contract | C18: 24
B19: % sites with Penalties / month | C19: 0.01
B20: UIT | C20: =4950/C14 -> 1302.6316
A22: PRONATEL EPAD SELVA - ITEM 2
A24: INFRAESTRUCTURE
B25: CAPEX REMOTE TERMINALS - VSAT
B26: Manufacturer Part # | C26: Product Code | D26: Description | E26: Qty | F26: Unit of Pricing | G26: Unit Price | H26: Ext. Price | I26: Unit Cost | J26: Ext. Cost | K26: Profit Margin | L26: Owner
A27: CAPEX | B27: 1505216-0332 | C27: HT2010 | D27: HT2010 Consumer Broadband Satellite Router, Ka Band only | E27: =$C$7 -> 270 | F27: ea | G27: =I27/0.7 -> 109.71429 | H27: =E27*G27 -> 29622.857 | I27: 76.8 | J27: =E27*I27 -> 20736 | K27: =1-(J27/H27) -> 0.3 | L27: HNS | M27: VSAT
A28: CAPEX | B28: 1506307-0001+1506307-0101 | C28: AN-120-SG-P1 + AN-120-SG-P2 | D28: 1.2m Ka-Band antenna, Single IFL | E28: 0 | F28: ea | G28: =I28/0.7 -> 426.52857 | H28: =E28*G28 -> 0 | I28: 298.57 | J28: =E28*I28 -> 0 | K28: =1-(J28/H28) -> #DIV/0! | L28: HNS | M28: VSAT
A29: CAPEX | B29: 1506689-1004 | C29: HB220-L | D29: 3W Multi-mode radio, Ka-Band, RHCP | E29: =$C$7 -> 270 | F29: ea | G29: =I29/0.7 -> 138.45714 | H29: =E29*G29 -> 37383.429 | I29: 96.92 | J29: =E29*I29 -> 26168.4 | K29: =1-(J29/H29) -> 0.3 | L29: HNS | M29: VSAT
A30: CAPEX | B30: 1506560-0012+1506561-0011 | C30: AN-90-KA1-NL-4PK + AN-90-KA2-4PK | D30: 90cm Ka-Band antenna, Single IFL, 4 PK- 4 antennas | E30: 67 | F30: ea | G30: =I30/0.7 -> 410.3 | H30: =E30*G30 -> 27490.1 | I30: 287.21 | J30: =E30*I30 -> 19243.07 | K30: =1-(J30/H30) -> 0.3 | L30: HNS | M30: VSAT
A31: CAPEX | B31: 1506560-0022+ 1506561-0021 | C31: AN-90-KA1-NL-1PK + AN-90-KA2-1PK | D31: 90cm Ka-Band antenna, Single IFL, 1 PK | E31: 2 | F31: ea | G31: =I31/0.7 -> 129.4 | H31: =E31*G31 -> 258.8 | I31: 90.58 | J31: =E31*I31 -> 181.16 | K31: =1-(J31/H31) -> 0.3 | L31: HNS | M31: VSAT
A32: CAPEX | C32: Antenna Mast | D32: Trimast Mount for 74cm and 90cm antenna | E32: 270 | F32: ea | G32: =I32/0.7 -> 20 | H32: =E32*G32 -> 5400 | I32: 14 | J32: =E32*I32 -> 3780 | K32: =1-(J32/H32) -> 0.3 | L32: HNS | M32: VSAT
A33: CAPEX | B33: 611604104 | C33: Antenna Mast | D33: 1.2m Ka antenna tri-mast mount | E33: 0 | F33: ea | G33: =I33/0.7 -> 70.714286 | H33: =E33*G33 -> 0 | I33: 49.5 | J33: =E33*I33 -> 0 | K33: =1-(J33/H33) -> #DIV/0! | L33: HNS | M33: VSAT
H34: =SUM(H27:H33) -> 100155.19 | J34: =SUM(J27:J33) -> 70108.63 | K34: =1-(J34/H34) -> 0.3
D35: Discount | E35: 0 | H35: =-H34*E35 -> 0
H36: =H34+H35 -> 100155.19 | J36: =J34 -> 70108.63 | K36: =1-(J36/H36) -> 0.3
B38: CAPEX REMOTE TERMINALS - SPARE VSAT (20 kits vandalism and 5% for operations)
B39: Manufacturer Part # | C39: Product Code | D39: Description | E39: Qty | F39: Unit of Pricing | G39: Unit Price | H39: Ext. Price | I39: Unit Cost | J39: Ext. Cost | K39: Profit Margin | L39: Owner
A40: CAPEX | B40: 1505216-0332 | C40: HT2010 | D40: HT2010 Consumer Broadband Satellite Router, Ka Band only | E40: =ROUNDUP($C$8*$C$7,0) -> 14 | F40: ea | G40: =I40/0.7 -> 109.71429 | H40: =E40*G40 -> 1536 | I40: 76.8 | J40: =E40*I40 -> 1075.2 | K40: =1-(J40/H40) -> 0.3 | L40: HNS | M40: VSAT
A41: CAPEX | B41: 1506307-0001+1506307-0101 | C41: AN-120-SG-P1 + AN-120-SG-P2 | D41: 1.2m Ka-Band antenna, Single IFL | E41: 0 | F41: ea | G41: =I41/0.7 -> 426.52857 | H41: =E41*G41 -> 0 | I41: 298.57 | J41: =E41*I41 -> 0 | K41: =1-(J41/H41) -> #DIV/0! | L41: HNS | M41: VSAT
A42: CAPEX | B42: 1506689-1004 | C42: HB220-L | D42: 3W Multi-mode radio, Ka-Band, RHCP | E42: =ROUNDUP($C$8*$C$7,0) -> 14 | F42: ea | G42: =I42/0.7 -> 138.45714 | H42: =E42*G42 -> 1938.4 | I42: 96.92 | J42: =E42*I42 -> 1356.88 | K42: =1-(J42/H42) -> 0.3 | L42: HNS | M42: VSAT
A43: CAPEX | B43: 1506560-0012+1506561-0011 | C43: AN-90-KA1-NL-4PK + AN-90-KA2-4PK | D43: 90cm Ka-Band antenna, Single IFL, 4 PK- 4 antennas | E43: 3 | F43: ea | G43: =I43/0.7 -> 410.3 | H43: =E43*G43 -> 1230.9 | I43: 287.21 | J43: =E43*I43 -> 861.63 | K43: =1-(J43/H43) -> 0.3 | L43: HNS | M43: VSAT
A44: CAPEX | B44: 1506560-0022+ 1506561-0021 | C44: AN-90-KA1-NL-1PK + AN-90-KA2-1PK | D44: 90cm Ka-Band antenna, Single IFL, 1 PK | E44: 2 | F44: ea | G44: =I44/0.7 -> 129.4 | H44: =E44*G44 -> 258.8 | I44: 90.58 | J44: =E44*I44 -> 181.16 | K44: =1-(J44/H44) -> 0.3 | L44: HNS | M44: VSAT
A45: CAPEX | C45: Antenna Mast | D45: Trimast Mount for 74cm and 90cm antenna | E45: 14 | F45: ea | G45: =I45/0.7 -> 20 | H45: =E45*G45 -> 280 | I45: 14 | J45: =E45*I45 -> 196 | K45: =1-(J45/H45) -> 0.3 | L45: HNS | M45: VSAT
A46: CAPEX | B46: 611604104 | C46: Antenna Mast | D46: 1.2m Ka antenna tri-mast mount | E46: 0 | F46: ea | G46: =I46/0.7 -> 70.714286 | H46: =E46*G46 -> 0 | I46: 49.5 | J46: =E46*I46 -> 0 | K46: =1-(J46/H46) -> #DIV/0! | L46: HNS | M46: VSAT
H47: =SUM(H40:H46) -> 5244.1 | J47: =SUM(J40:J46) -> 3670.87 | K47: =1-(J47/H47) -> 0.3
D48: Discount | E48: 0 | H48: =-H47*E48 -> 0
H49: =H47+H48 -> 5244.1 | J49: =J47 -> 3670.87 | K49: =1-(J49/H49) -> 0.3
B50: SOLAR PANELS
B51: Vendor | C51: Product Code | D51: Description | E51: Qty | F51: Unit of Pricing | G51: Unit Price | H51: Ext. Price | I51: Unit Cost | J51: Ext. Cost | K51: Profit Margin | L51: Owner
A52: CAPEX | D52: Solar Panel | E52: =C7 -> 270 | F52: ea | G52: =I52/0.75 -> #REF! | H52: =E52*G52 -> #REF! | I52: =#REF!+#REF! -> #REF! | J52: =E52*I52 -> #REF! | K52: =1-(J52/H52) -> #REF! | L52: HDP
A53: CAPEX | E53: =ROUNDUP($C$8*$C$7,0) -> 14 | F53: ea | G53: =I53/0.75 -> #REF! | H53: =E53*G53 -> #REF! | I53: =#REF!+#REF! -> #REF! | J53: =E53*I53 -> #REF! | K53: =1-(J53/H53) -> #REF! | L53: HDP
H54: =SUM(H50:H53) -> #REF! | J54: =SUM(J50:J53) -> #REF! | K54: =1-(J54/H54) -> #REF!
D55: Discount | E55: 0 | H55: =-H54*E55 -> #REF!
H56: =H54+H55 -> #REF! | J56: =J54 -> #REF! | K56: =1-(J56/H56) -> #REF!
B58: CABINETS
B59: Vendor | C59: Product Code | D59: Description | E59: Qty | F59: Unit of Pricing | G59: Unit Price | H59: Ext. Price | I59: Unit Cost | J59: Ext. Cost | K59: Profit Margin | L59: Owner
A60: CAPEX | D60: Cabinet Outdoor | E60: =$C$7 -> 270 | F60: ea | G60: =I60/0.75 -> #REF! | H60: =E60*G60 -> #REF! | I60: =#REF! -> #REF! | J60: =E60*I60 -> #REF! | K60: =1-(J60/H60) -> #REF! | L60: HDP
A61: CAPEX | E61: =ROUNDUP($C$8*$C$7,0) -> 14 | F61: ea | G61: =I61/0.75 -> #REF! | H61: =E61*G61 -> #REF! | I61: =#REF! -> #REF! | J61: =E61*I61 -> #REF! | K61: =1-(J61/H61) -> #REF! | L61: HDP
H62: =SUM(H58:H61) -> #REF! | J62: =SUM(J58:J61) -> #REF! | K62: =1-(J62/H62) -> #REF!
D63: Discount | E63: 0 | H63: =-H62*E63 -> #REF!
H64: =H62+H63 -> #REF! | J64: =J62 -> #REF! | K64: =1-(J64/H64) -> #REF!
B66: ROUTERS MIKROTIK
B67: Vendor | C67: Product Code | D67: Description | E67: Qty | F67: Unit of Pricing | G67: Unit Price | H67: Ext. Price | I67: Unit Cost | J67: Ext. Cost | K67: Profit Margin | L67: Owner
A68: CAPEX | B68: MIKROTIK | C68: RB760IGS | D68: 5x Gigabit Ethernet, SFP, Dual Core 880MHz CPU, 256MB RAM, USB, microSD, RouterOS L4, IPsec hardware encryption support and The Dude server package | E68: =$C$7 -> 270 | F68: ea | G68: =I68/0.75 -> #REF! | H68: =E68*G68 -> #REF! | I68: =#REF! -> #REF! | J68: =E68*I68 -> #REF! | K68: =1-(J68/H68) -> #REF! | L68: HDP
A69: CAPEX | B69: MIKROTIK | C69: RB760IGS | D69: 5x Gigabit Ethernet, SFP, Dual Core 880MHz CPU, 256MB RAM, USB, microSD, RouterOS L4, IPsec hardware encryption support and The Dude server package (20 kits vandalism and 5% for operations) | E69: =ROUNDUP($C$8*$C$7,0) -> 14 | F69: ea | G69: =I69/0.75 -> #REF! | H69: =E69*G69 -> #REF! | I69: =#REF! -> #REF! | J69: =E69*I69 -> #REF! | K69: =1-(J69/H69) -> #REF! | L69: HDP
H70: =SUM(H66:H69) -> #REF! | J70: =SUM(J66:J69) -> #REF! | K70: =1-(J70/H70) -> #REF!
D71: Discount | E71: 0 | H71: =-H70*E71 -> #REF!
H72: =H70+H71 -> #REF! | J72: =J70 -> #REF! | K72: =1-(J72/H72) -> #REF!
B74: DESKTOP COMPUTER
B75: Vendor | C75: Product Code | D75: Description | E75: Qty | F75: Unit of Pricing | G75: Unit Price | H75: Ext. Price | I75: Unit Cost | J75: Ext. Cost | K75: Profit Margin | L75: Owner
A76: CAPEX | D76: Computadora para Monitoreo | E76: 1 | F76: ea | G76: =I76/0.75 -> 6666.6667 | H76: =E76*G76 -> 6666.6667 | I76: 5000 | J76: =E76*I76 -> 5000 | K76: =1-(J76/H76) -> 0.25 | L76: HDP
H77: =SUM(H74:H76) -> 6666.6667 | J77: =SUM(J74:J76) -> 5000 | K77: =1-(J77/H77) -> 0.25
D78: Discount | E78: 0 | H78: =-H77*E78 -> 0
H79: =H77+H78 -> 6666.6667 | J79: =J77 -> 5000 | K79: =1-(J79/H79) -> 0.25
B81: IBOSS-WEB FILTERING SOLUTION
B82: Vendor | C82: Product Code | D82: Description | E82: Qty | F82: Unit of Pricing | G82: Unit Price | H82: Ext. Price | I82: Unit Cost | J82: Ext. Cost | K82: Profit Margin | L82: Owner
A83: CAPEX | D83: FORTINET ITEM 1 | E83: 0 | F83: ea | G83: =I83/0.75 -> 0 | H83: =E83*G83*$C$18 -> 0 | I83: 0 | J83: =E83*I83*$C$18 -> 0 | K83: =1-(J83/H83) -> #DIV/0! | L83: HDP
A84: CAPEX | D84: FORTINET ITEM 2 | E84: 1 | F84: ea | G84: =I84/0.75 -> #REF! | H84: =E84*G84 -> #REF! | I84: =#REF! -> #REF! | J84: =E84*I84 -> #REF! | K84: =1-(J84/H84) -> #REF! | L84: HDP
A85: CAPEX | D85: FORTINET ITEM 3 | E85: 0 | F85: ea | G85: =I85/0.75 -> 0 | H85: =E85*G85*$C$18 -> 0 | I85: 0 | J85: =E85*I85*$C$18 -> 0 | K85: =1-(J85/H85) -> #DIV/0! | L85: HDP
A86: CAPEX | D86: FORTINET ITEM 4 | E86: 0 | F86: ea | G86: =I86/0.75 -> 0 | H86: =E86*G86*$C$18 -> 0 | I86: 0 | J86: =E86*I86*$C$18 -> 0 | K86: =1-(J86/H86) -> #DIV/0! | L86: HDP
A87: CAPEX | D87: FORTINET ITEM 5 | E87: 0 | F87: ea | G87: =I87/0.75 -> 0 | H87: =E87*G87*$C$18 -> 0 | I87: 0 | J87: =E87*I87*$C$18 -> 0 | K87: =1-(J87/H87) -> #DIV/0! | L87: HDP
A88: CAPEX | D88: FORTINET ALL ITEMS | E88: 0 | F88: ea | G88: =I88/0.75 -> 0 | H88: =E88*G88 -> 0 | I88: 0 | J88: =E88*I88 -> 0 | K88: =1-(J88/H88) -> #DIV/0! | L88: HDP
A89: CAPEX | F89: ea | G89: =I89/0.75 -> 0 | H89: =E89*G89 -> 0 | J89: =E89*I89 -> 0 | K89: =1-(J89/H89) -> #DIV/0! | L89: HDP
A90: CAPEX | F90: ea | G90: =I90/0.75 -> 0 | H90: =E90*G90 -> 0 | J90: =E90*I90 -> 0 | K90: =1-(J90/H90) -> #DIV/0! | L90: HDP
A91: CAPEX | F91: ea | G91: =I91/0.75 -> 0 | H91: =E91*G91 -> 0 | J91: =E91*I91 -> 0 | K91: =1-(J91/H91) -> #DIV/0! | L91: HDP
F92: ea | G92: =I92/0.6 -> 0 | H92: =E92*G92 -> 0 | I92: 0 | J92: =E92*I92 -> 0 | K92: =1-(J92/H92) -> #DIV/0! | L92: HDP
H93: =SUM(H83:H92) -> #REF! | J93: =SUM(J83:J92) -> #REF! | K93: =1-(J93/H93) -> #REF!
D94: Discount | E94: 0 | H94: =-H93*E94 -> #REF!
H95: =H93+H94 -> #REF! | J95: =J93 -> #REF! | K95: =1-(J95/H95) -> #REF!
B96: ACCESS POINTS
B97: Vendor | C97: Product Code | D97: Description | E97: Qty | F97: Unit of Pricing | G97: Unit Price | H97: Ext. Price | I97: Unit Cost | J97: Ext. Cost | K97: Profit Margin | L97: Owner
A98: CAPEX | B98: CAMBIUM | D98: Outdoor Dual radio WiFi 6 AP Omni 2x2, GbE. RW | E98: =C7*2 -> 540 | F98: ea | G98: =I98/0.75 -> #REF! | H98: =E98*G98 -> #REF! | I98: =#REF! -> #REF! | J98: =E98*I98 -> #REF! | K98: =1-(J98/H98) -> #REF! | L98: HDP
A99: CAPEX | B99: CAMBIUM | D99: PoE, 60W, 56V, 5GbE DC Injector, Indoor, Energy Level 6 Supply, accepts C5 connector | E99: =C7*2 -> 540 | F99: ea | G99: =I99/0.75 -> #REF! | H99: =E99*G99 -> #REF! | I99: =#REF! -> #REF! | J99: =E99*I99 -> #REF! | K99: =1-(J99/H99) -> #REF! | L99: HDP
A100: CAPEX | B100: CAMBIUM | D100: AC line cord, US Type B, 720mm, C5 connector | E100: =C7*2 -> 540 | F100: ea | G100: =I100/0.75 -> #REF! | H100: =E100*G100 -> #REF! | I100: =#REF! -> #REF! | J100: =E100*I100 -> #REF! | K100: =1-(J100/H100) -> #REF! | L100: HDP
A101: CAPEX | B101: CAMBIUM | D101: XMS-Cloud 3-year subscription for Education: 2 and 3-radio AP with all EasyPass modules and Cambium Care Advanced Support | E101: =C7*2 -> 540 | F101: ea | G101: =I101/0.75 -> #REF! | H101: =E101*G101 -> #REF! | I101: =#REF! -> #REF! | J101: =E101*I101 -> #REF! | K101: =1-(J101/H101) -> #REF! | L101: HDP
A102: CAPEX | B102: CAMBIUM | D102: Outdoor Dual radio WiFi 6 AP Omni 2x2, GbE. RW | E102: =ROUNDUP($C$8*$C$7,0)*2 -> 28 | F102: ea | G102: =I102/0.75 -> #REF! | H102: =E102*G102 -> #REF! | I102: =#REF! -> #REF! | J102: =E102*I102 -> #REF! | K102: =1-(J102/H102) -> #REF! | L102: HDP
A103: CAPEX | B103: CAMBIUM | D103: PoE, 60W, 56V, 5GbE DC Injector, Indoor, Energy Level 6 Supply, accepts C5 connector | E103: =ROUNDUP($C$8*$C$7,0)*2 -> 28 | F103: ea | G103: =I103/0.75 -> #REF! | H103: =E103*G103 -> #REF! | I103: =#REF! -> #REF! | J103: =E103*I103 -> #REF! | K103: =1-(J103/H103) -> #REF! | L103: HDP
A104: CAPEX | B104: CAMBIUM | D104: AC line cord, US Type B, 720mm, C5 connector | E104: =ROUNDUP($C$8*$C$7,0)*2 -> 28 | F104: ea | G104: =I104/0.75 -> #REF! | H104: =E104*G104 -> #REF! | I104: =#REF! -> #REF! | J104: =E104*I104 -> #REF! | K104: =1-(J104/H104) -> #REF! | L104: HDP
E105: 0 | F105: ea | G105: =I105/0.75 -> 0 | H105: =E105*G105 -> 0 | I105: 0 | J105: =E105*I105 -> 0 | K105: =1-(J105/H105) -> #DIV/0! | L105: HDP
E106: 0 | F106: ea | G106: =I106/0.75 -> 0 | H106: =E106*G106 -> 0 | I106: 0 | J106: =E106*I106 -> 0 | K106: =1-(J106/H106) -> #DIV/0! | L106: HDP
E107: 0 | F107: ea | G107: =I107/0.75 -> 0 | H107: =E107*G107 -> 0 | I107: 0 | J107: =E107*I107 -> 0 | K107: =1-(J107/H107) -> #DIV/0! | L107: HDP
F108: ea | G108: =I108/0.6 -> 0 | H108: =E108*G108 -> 0 | I108: 0 | J108: =E108*I108 -> 0 | K108: =1-(J108/H108) -> #DIV/0! | L108: HDP
H109: =SUM(H98:H108) -> #REF! | J109: =SUM(J98:J108) -> #REF! | K109: =1-(J109/H109) -> #REF!
...

Sheet QTO EPAD SELVA - ITEM 3
A1: QTO PRONATEL-EPAD SELVA - ITEM 3
A4: ITEM 3 | B4: Inputs | G4: PRICE | H4: COST | I4: MARGIN
B5: HUGHES T19 Number of Sites | C5: 21 | F5: CAPEX | G5: =SUMIF(A26:A175,"CAPEX",H26:H175) -> #REF! | H5: =SUMIF(A26:A175,"CAPEX",J26:J175) -> #REF! | I5: =1-(H5/G5) -> #REF!
B6: Sites out of coverage | C6: 341 | F6: OPEX | G6: =SUMIF(A26:A175,"OPEX",H26:H175) -> #REF! | H6: =SUMIF(A26:A175,"OPEX",J26:J175) -> #REF! | I6: =1-(H6/G6) -> #REF!
B7: Number of Sites | C7: =C5+C6 -> 362 | G7: =SUM(G5:G6) -> #REF! | H7: =SUM(H5:H6) -> #REF! | I7: =1-(H7/G7) -> #REF!
B8: Remote Spares | C8: 0.05
B9: Total of Spares
B10: Total capacity T19 (Mbps) | C10: 52.5
B11: Total capacity SES-17 (Mbps) | C11: 852.5
B12: Total Ka band Capacity (Mbps) | C12: =C10+C11 -> 905 | G12: Price x Site x Month | H12: Cost x Site x Month | I12: MARGIN
B13: Average Mbps per Site | C13: =C12/C7 -> 2.5 | G13: =G7/C7/C18 -> #REF! | H13: =H7/C7/C18 -> #REF! | I13: =1-(H13/G13) -> #REF!
B14: Tipo de Cambio | C14: 3.8
B15: Terminal Unit Price (USD) | C15: =G27+G28+G29+G33 -> 745.41429
B16: COST - SES Ka band Mbps / Month (USD) | C16: 155
B17: COST - HUGHES Ka band Mbps / Month (USD) | C17: 55
B18: Contract | C18: 24
B19: % sites with Penalties / month | C19: 0.01
B20: UIT | C20: =4950/C14 -> 1302.6316
A22: PRONATEL EPAD SELVA - ITEM 3
A24: INFRAESTRUCTURE
B25: CAPEX REMOTE TERMINALS - VSAT
B26: Manufacturer Part # | C26: Product Code | D26: Description | E26: Qty | F26: Unit of Pricing | G26: Unit Price | H26: Ext. Price | I26: Unit Cost | J26: Ext. Cost | K26: Profit Margin | L26: Owner
A27: CAPEX | B27: 1505216-0332 | C27: HT2010 | D27: HT2010 Consumer Broadband Satellite Router, Ka Band only | E27: =$C$7 -> 362 | F27: ea | G27: =I27/0.7 -> 109.71429 | H27: =E27*G27 -> 39716.571 | I27: 76.8 | J27: =E27*I27 -> 27801.6 | K27: =1-(J27/H27) -> 0.3 | L27: HNS | M27: VSAT
A28: CAPEX | B28: 1506307-0001+1506307-0101 | C28: AN-120-SG-P1 + AN-120-SG-P2 | D28: 1.2m Ka-Band antenna, Single IFL | E28: 0 | F28: ea | G28: =I28/0.7 -> 426.52857 | H28: =E28*G28 -> 0 | I28: 298.57 | J28: =E28*I28 -> 0 | K28: =1-(J28/H28) -> #DIV/0! | L28: HNS | M28: VSAT
A29: CAPEX | B29: 1506689-1004 | C29: HB220-L | D29: 3W Multi-mode radio, Ka-Band, RHCP | E29: =$C$7 -> 362 | F29: ea | G29: =I29/0.7 -> 138.45714 | H29: =E29*G29 -> 50121.486 | I29: 96.92 | J29: =E29*I29 -> 35085.04 | K29: =1-(J29/H29) -> 0.3 | L29: HNS | M29: VSAT
A30: CAPEX | B30: 1506560-0012+1506561-0011 | C30: AN-90-KA1-NL-4PK + AN-90-KA2-4PK | D30: 90cm Ka-Band antenna, Single IFL, 4 PK- 4 antennas | E30: 90 | F30: ea | G30: =I30/0.7 -> 410.3 | H30: =E30*G30 -> 36927 | I30: 287.21 | J30: =E30*I30 -> 25848.9 | K30: =1-(J30/H30) -> 0.3 | L30: HNS | M30: VSAT
A31: CAPEX | B31: 1506560-0022+ 1506561-0021 | C31: AN-90-KA1-NL-1PK + AN-90-KA2-1PK | D31: 90cm Ka-Band antenna, Single IFL, 1 PK | E31: 2 | F31: ea | G31: =I31/0.7 -> 129.4 | H31: =E31*G31 -> 258.8 | I31: 90.58 | J31: =E31*I31 -> 181.16 | K31: =1-(J31/H31) -> 0.3 | L31: HNS | M31: VSAT
A32: CAPEX | C32: Antenna Mast | D32: Trimast Mount for 74cm and 90cm antenna | E32: 362 | F32: ea | G32: =I32/0.7 -> 20 | H32: =E32*G32 -> 7240 | I32: 14 | J32: =E32*I32 -> 5068 | K32: =1-(J32/H32) -> 0.3 | L32: HNS | M32: VSAT
A33: CAPEX | B33: 611604104 | C33: Antenna Mast | D33: 1.2m Ka antenna tri-mast mount | E33: 0 | F33: ea | G33: =I33/0.7 -> 70.714286 | H33: =E33*G33 -> 0 | I33: 49.5 | J33: =E33*I33 -> 0 | K33: =1-(J33/H33) -> #DIV/0! | L33: HNS | M33: VSAT
H34: =SUM(H27:H33) -> 134263.86 | J34: =SUM(J27:J33) -> 93984.7 | K34: =1-(J34/H34) -> 0.3
D35: Discount | E35: 0 | H35: =-H34*E35 -> 0
H36: =H34+H35 -> 134263.86 | J36: =J34 -> 93984.7 | K36: =1-(J36/H36) -> 0.3
B38: CAPEX REMOTE TERMINALS - SPARE VSAT (20 kits vandalism and 5% for operations)
B39: Manufacturer Part # | C39: Product Code | D39: Description | E39: Qty | F39: Unit of Pricing | G39: Unit Price | H39: Ext. Price | I39: Unit Cost | J39: Ext. Cost | K39: Profit Margin | L39: Owner
A40: CAPEX | B40: 1505216-0332 | C40: HT2010 | D40: HT2010 Consumer Broadband Satellite Router, Ka Band only | E40: =ROUNDUP($C$8*$C$7,0) -> 19 | F40: ea | G40: =I40/0.7 -> 109.71429 | H40: =E40*G40 -> 2084.5714 | I40: 76.8 | J40: =E40*I40 -> 1459.2 | K40: =1-(J40/H40) -> 0.3 | L40: HNS | M40: VSAT
A41: CAPEX | B41: 1506307-0001+1506307-0101 | C41: AN-120-SG-P1 + AN-120-SG-P2 | D41: 1.2m Ka-Band antenna, Single IFL | E41: 0 | F41: ea | G41: =I41/0.7 -> 426.52857 | H41: =E41*G41 -> 0 | I41: 298.57 | J41: =E41*I41 -> 0 | K41: =1-(J41/H41) -> #DIV/0! | L41: HNS | M41: VSAT
A42: CAPEX | B42: 1506689-1004 | C42: HB220-L | D42: 3W Multi-mode radio, Ka-Band, RHCP | E42: =ROUNDUP($C$8*$C$7,0) -> 19 | F42: ea | G42: =I42/0.7 -> 138.45714 | H42: =E42*G42 -> 2630.6857 | I42: 96.92 | J42: =E42*I42 -> 1841.48 | K42: =1-(J42/H42) -> 0.3 | L42: HNS | M42: VSAT
A43: CAPEX | B43: 1506560-0012+1506561-0011 | C43: AN-90-KA1-NL-4PK + AN-90-KA2-4PK | D43: 90cm Ka-Band antenna, Single IFL, 4 PK- 4 antennas | E43: 4 | F43: ea | G43: =I43/0.7 -> 410.3 | H43: =E43*G43 -> 1641.2 | I43: 287.21 | J43: =E43*I43 -> 1148.84 | K43: =1-(J43/H43) -> 0.3 | L43: HNS | M43: VSAT
A44: CAPEX | B44: 1506560-0022+ 1506561-0021 | C44: AN-90-KA1-NL-1PK + AN-90-KA2-1PK | D44: 90cm Ka-Band antenna, Single IFL, 1 PK | E44: 3 | F44: ea | G44: =I44/0.7 -> 129.4 | H44: =E44*G44 -> 388.2 | I44: 90.58 | J44: =E44*I44 -> 271.74 | K44: =1-(J44/H44) -> 0.3 | L44: HNS | M44: VSAT
A45: CAPEX | C45: Antenna Mast | D45: Trimast Mount for 74cm and 90cm antenna | E45: 19 | F45: ea | G45: =I45/0.7 -> 20 | H45: =E45*G45 -> 380 | I45: 14 | J45: =E45*I45 -> 266 | K45: =1-(J45/H45) -> 0.3 | L45: HNS | M45: VSAT
A46: CAPEX | B46: 611604104 | C46: Antenna Mast | D46: 1.2m Ka antenna tri-mast mount | E46: 0 | F46: ea | G46: =I46/0.7 -> 70.714286 | H46: =E46*G46 -> 0 | I46: 49.5 | J46: =E46*I46 -> 0 | K46: =1-(J46/H46) -> #DIV/0! | L46: HNS | M46: VSAT
H47: =SUM(H40:H46) -> 7124.6571 | J47: =SUM(J40:J46) -> 4987.26 | K47: =1-(J47/H47) -> 0.3
D48: Discount | E48: 0 | H48: =-H47*E48 -> 0
H49: =H47+H48 -> 7124.6571 | J49: =J47 -> 4987.26 | K49: =1-(J49/H49) -> 0.3
B50: SOLAR PANELS
B51: Vendor | C51: Product Code | D51: Description | E51: Qty | F51: Unit of Pricing | G51: Unit Price | H51: Ext. Price | I51: Unit Cost | J51: Ext. Cost | K51: Profit Margin | L51: Owner
A52: CAPEX | D52: Solar Panel | E52: =C7 -> 362 | F52: ea | G52: =I52/0.75 -> #REF! | H52: =E52*G52 -> #REF! | I52: =#REF!+#REF! -> #REF! | J52: =E52*I52 -> #REF! | K52: =1-(J52/H52) -> #REF! | L52: HDP
A53: CAPEX | E53: =ROUNDUP($C$8*$C$7,0) -> 19 | F53: ea | G53: =I53/0.75 -> #REF! | H53: =E53*G53 -> #REF! | I53: =#REF!+#REF! -> #REF! | J53: =E53*I53 -> #REF! | K53: =1-(J53/H53) -> #REF! | L53: HDP
H54: =SUM(H50:H53) -> #REF! | J54: =SUM(J50:J53) -> #REF! | K54: =1-(J54/H54) -> #REF!
D55: Discount | E55: 0 | H55: =-H54*E55 -> #REF!
H56: =H54+H55 -> #REF! | J56: =J54 -> #REF! | K56: =1-(J56/H56) -> #REF!
B58: CABINETS
B59: Vendor | C59: Product Code | D59: Description | E59: Qty | F59: Unit of Pricing | G59: Unit Price | H59: Ext. Price | I59: Unit Cost | J59: Ext. Cost | K59: Profit Margin | L59: Owner
A60: CAPEX | D60: Cabinet Outdoor | E60: =$C$7 -> 362 | F60: ea | G60: =I60/0.75 -> #REF! | H60: =E60*G60 -> #REF! | I60: =#REF! -> #REF! | J60: =E60*I60 -> #REF! | K60: =1-(J60/H60) -> #REF! | L60: HDP
A61: CAPEX | E61: =ROUNDUP($C$8*$C$7,0) -> 19 | F61: ea | G61: =I61/0.75 -> #REF! | H61: =E61*G61 -> #REF! | I61: =#REF! -> #REF! | J61: =E61*I61 -> #REF! | K61: =1-(J61/H61) -> #REF! | L61: HDP
H62: =SUM(H58:H61) -> #REF! | J62: =SUM(J58:J61) -> #REF! | K62: =1-(J62/H62) -> #REF!
D63: Discount | E63: 0 | H63: =-H62*E63 -> #REF!
H64: =H62+H63 -> #REF! | J64: =J62 -> #REF! | K64: =1-(J64/H64) -> #REF!
B66: ROUTERS MIKROTIK
B67: Vendor | C67: Product Code | D67: Description | E67: Qty | F67: Unit of Pricing | G67: Unit Price | H67: Ext. Price | I67: Unit Cost | J67: Ext. Cost | K67: Profit Margin | L67: Owner
A68: CAPEX | B68: MIKROTIK | C68: RB760IGS | D68: 5x Gigabit Ethernet, SFP, Dual Core 880MHz CPU, 256MB RAM, USB, microSD, RouterOS L4, IPsec hardware encryption support and The Dude server package | E68: =$C$7 -> 362 | F68: ea | G68: =I68/0.75 -> #REF! | H68: =E68*G68 -> #REF! | I68: =#REF! -> #REF! | J68: =E68*I68 -> #REF! | K68: =1-(J68/H68) -> #REF! | L68: HDP
A69: CAPEX | B69: MIKROTIK | C69: RB760IGS | D69: 5x Gigabit Ethernet, SFP, Dual Core 880MHz CPU, 256MB RAM, USB, microSD, RouterOS L4, IPsec hardware encryption support and The Dude server package (20 kits vandalism and 5% for operations) | E69: =ROUNDUP($C$8*$C$7,0) -> 19 | F69: ea | G69: =I69/0.75 -> #REF! | H69: =E69*G69 -> #REF! | I69: =#REF! -> #REF! | J69: =E69*I69 -> #REF! | K69: =1-(J69/H69) -> #REF! | L69: HDP
H70: =SUM(H66:H69) -> #REF! | J70: =SUM(J66:J69) -> #REF! | K70: =1-(J70/H70) -> #REF!
D71: Discount | E71: 0 | H71: =-H70*E71 -> #REF!
H72: =H70+H71 -> #REF! | J72: =J70 -> #REF! | K72: =1-(J72/H72) -> #REF!
B74: DESKTOP COMPUTER
B75: Vendor | C75: Product Code | D75: Description | E75: Qty | F75: Unit of Pricing | G75: Unit Price | H75: Ext. Price | I75: Unit Cost | J75: Ext. Cost | K75: Profit Margin | L75: Owner
A76: CAPEX | D76: Computadora para Monitoreo | E76: 1 | F76: ea | G76: =I76/0.75 -> 6666.6667 | H76: =E76*G76 -> 6666.6667 | I76: 5000 | J76: =E76*I76 -> 5000 | K76: =1-(J76/H76) -> 0.25 | L76: HDP
H77: =SUM(H74:H76) -> 6666.6667 | J77: =SUM(J74:J76) -> 5000 | K77: =1-(J77/H77) -> 0.25
D78: Discount | E78: 0 | H78: =-H77*E78 -> 0
H79: =H77+H78 -> 6666.6667 | J79: =J77 -> 5000 | K79: =1-(J79/H79) -> 0.25
B81: IBOSS-WEB FILTERING SOLUTION
B82: Vendor | C82: Product Code | D82: Description | E82: Qty | F82: Unit of Pricing | G82: Unit Price | H82: Ext. Price | I82: Unit Cost | J82: Ext. Cost | K82: Profit Margin | L82: Owner
A83: CAPEX | D83: FORTINET ITEM 1 | E83: 0 | F83: ea | G83: =I83/0.75 -> 0 | H83: =E83*G83*$C$18 -> 0 | I83: 0 | J83: =E83*I83*$C$18 -> 0 | K83: =1-(J83/H83) -> #DIV/0! | L83: HDP
A84: CAPEX | D84: FORTINET ITEM 2 | E84: 0 | F84: ea | G84: =I84/0.75 -> 0 | H84: =E84*G84 -> 0 | I84: 0 | J84: =E84*I84 -> 0 | K84: =1-(J84/H84) -> #DIV/0! | L84: HDP
A85: CAPEX | D85: FORTINET ITEM 3 | E85: 1 | F85: ea | G85: =I85/0.75 -> #REF! | H85: =E85*G85 -> #REF! | I85: =#REF! -> #REF! | J85: =E85*I85 -> #REF! | K85: =1-(J85/H85) -> #REF! | L85: HDP
A86: CAPEX | D86: FORTINET ITEM 4 | E86: 0 | F86: ea | G86: =I86/0.75 -> 0 | H86: =E86*G86*$C$18 -> 0 | I86: 0 | J86: =E86*I86*$C$18 -> 0 | K86: =1-(J86/H86) -> #DIV/0! | L86: HDP
A87: CAPEX | D87: FORTINET ITEM 5 | E87: 0 | F87: ea | G87: =I87/0.75 -> 0 | H87: =E87*G87*$C$18 -> 0 | I87: 0 | J87: =E87*I87*$C$18 -> 0 | K87: =1-(J87/H87) -> #DIV/0! | L87: HDP
A88: CAPEX | D88: FORTINET ALL ITEMS | E88: 0 | F88: ea | G88: =I88/0.75 -> 0 | H88: =E88*G88 -> 0 | I88: 0 | J88: =E88*I88 -> 0 | K88: =1-(J88/H88) -> #DIV/0! | L88: HDP
A89: CAPEX | F89: ea | G89: =I89/0.75 -> 0 | H89: =E89*G89 -> 0 | J89: =E89*I89 -> 0 | K89: =1-(J89/H89) -> #DIV/0! | L89: HDP
A90: CAPEX | F90: ea | G90: =I90/0.75 -> 0 | H90: =E90*G90 -> 0 | J90: =E90*I90 -> 0 | K90: =1-(J90/H90) -> #DIV/0! | L90: HDP
A91: CAPEX | F91: ea | G91: =I91/0.75 -> 0 | H91: =E91*G91 -> 0 | J91: =E91*I91 -> 0 | K91: =1-(J91/H91) -> #DIV/0! | L91: HDP
F92: ea | G92: =I92/0.6 -> 0 | H92: =E92*G92 -> 0 | I92: 0 | J92: =E92*I92 -> 0 | K92: =1-(J92/H92) -> #DIV/0! | L92: HDP
H93: =SUM(H83:H92) -> #REF! | J93: =SUM(J83:J92) -> #REF! | K93: =1-(J93/H93) -> #REF!
D94: Discount | E94: 0 | H94: =-H93*E94 -> #REF!
H95: =H93+H94 -> #REF! | J95: =J93 -> #REF! | K95: =1-(J95/H95) -> #REF!
B96: ACCESS POINTS
B97: Vendor | C97: Product Code | D97: Description | E97: Qty | F97: Unit of Pricing | G97: Unit Price | H97: Ext. Price | I97: Unit Cost | J97: Ext. Cost | K97: Profit Margin | L97: Owner
A98: CAPEX | B98: CAMBIUM | D98: Outdoor Dual radio WiFi 6 AP Omni 2x2, GbE. RW | E98: =C7*2 -> 724 | F98: ea | G98: =I98/0.75 -> #REF! | H98: =E98*G98 -> #REF! | I98: =#REF! -> #REF! | J98: =E98*I98 -> #REF! | K98: =1-(J98/H98) -> #REF! | L98: HDP
A99: CAPEX | B99: CAMBIUM | D99: PoE, 60W, 56V, 5GbE DC Injector, Indoor, Energy Level 6 Supply, accepts C5 connector | E99: =C7*2 -> 724 | F99: ea | G99: =I99/0.75 -> #REF! | H99: =E99*G99 -> #REF! | I99: =#REF! -> #REF! | J99: =E99*I99 -> #REF! | K99: =1-(J99/H99) -> #REF! | L99: HDP
A100: CAPEX | B100: CAMBIUM | D100: AC line cord, US Type B, 720mm, C5 connector | E100: =C7*2 -> 724 | F100: ea | G100: =I100/0.75 -> #REF! | H100: =E100*G100 -> #REF! | I100: =#REF! -> #REF! | J100: =E100*I100 -> #REF! | K100: =1-(J100/H100) -> #REF! | L100: HDP
A101: CAPEX | B101: CAMBIUM | D101: XMS-Cloud 3-year subscription for Education: 2 and 3-radio AP with all EasyPass modules and Cambium Care Advanced Support | E101: =C7*2 -> 724 | F101: ea | G101: =I101/0.75 -> #REF! | H101: =E101*G101 -> #REF! | I101: =#REF! -> #REF! | J101: =E101*I101 -> #REF! | K101: =1-(J101/H101) -> #REF! | L101: HDP
A102: CAPEX | B102: CAMBIUM | D102: Outdoor Dual radio WiFi 6 AP Omni 2x2, GbE. RW | E102: =ROUNDUP($C$8*$C$7,0)*2 -> 38 | F102: ea | G102: =I102/0.75 -> #REF! | H102: =E102*G102 -> #REF! | I102: =#REF! -> #REF! | J102: =E102*I102 -> #REF! | K102: =1-(J102/H102) -> #REF! | L102: HDP
A103: CAPEX | B103: CAMBIUM | D103: PoE, 60W, 56V, 5GbE DC Injector, Indoor, Energy Level 6 Supply, accepts C5 connector | E103: =ROUNDUP($C$8*$C$7,0)*2 -> 38 | F103: ea | G103: =I103/0.75 -> #REF! | H103: =E103*G103 -> #REF! | I103: =#REF! -> #REF! | J103: =E103*I103 -> #REF! | K103: =1-(J103/H103) -> #REF! | L103: HDP
A104: CAPEX | B104: CAMBIUM | D104: AC line cord, US Type B, 720mm, C5 connector | E104: =ROUNDUP($C$8*$C$7,0)*2 -> 38 | F104: ea | G104: =I104/0.75 -> #REF! | H104: =E104*G104 -> #REF! | I104: =#REF! -> #REF! | J104: =E104*I104 -> #REF! | K104: =1-(J104/H104) -> #REF! | L104: HDP
E105: 0 | F105: ea | G105: =I105/0.75 -> 0 | H105: =E105*G105 -> 0 | I105: 0 | J105: =E105*I105 -> 0 | K105: =1-(J105/H105) -> #DIV/0! | L105: HDP
E106: 0 | F106: ea | G106: =I106/0.75 -> 0 | H106: =E106*G106 -> 0 | I106: 0 | J106: =E106*I106 -> 0 | K106: =1-(J106/H106) -> #DIV/0! | L106: HDP
E107: 0 | F107: ea | G107: =I107/0.75 -> 0 | H107: =E107*G107 -> 0 | I107: 0 | J107: =E107*I107 -> 0 | K107: =1-(J107/H107) -> #DIV/0! | L107: HDP
F108: ea | G108: =I108/0.6 -> 0 | H108: =E108*G108 -> 0 | I108: 0 | J108: =E108*I108 -> 0 | K108: =1-(J108/H108) -> #DIV/0! | L108: HDP
H109: =SUM(H98:H108) -> #REF! | J109: =SUM(J98:J108) -> #REF! | K109: =1-(J109/H109) -> #REF!
...
