Workbook
Name Access_Points: #REF!
Name Cabinets: #REF!
Name CustomerView: #REF!
Name Desktop_Pc: #REF!
Name Digital_Repository: #REF!
Name Installation___Support: #REF!
Name Managed_Capacity: #REF!
Name Network_O_M: #REF!
Name QTO_DB: Table1[]
Name Routers_Microtik: #REF!
Name Solar_Panels: #REF!
Name VSAT: #REF!
Name Web_Filetring: #REF!

Sheet QTO DB
A1: Inputs
A2: Client: | C2: MINEDU
B3: Country | C3: PERU
B4: Proposal Manager: | C4: JUAN ASTO | F4: PRICE | G4: COST | H4: MARGIN
A5: HUGHES T19 Number of Sites | C5: 1204 | E5: CAPEX | F5: =SUMIF(A24:A25,"CAPEX",M24:M25) -> 146337.6 | G5: =SUMIF(A24:A25,"CAPEX",O24:O25) -> 102436.32 | H5: =1-(G5/F5) -> 0.3
A6: Sites out of coverage | C6: 0 | E6: OPEX | F6: =SUMIF(A24:A25,"OPEX",M24:M25) -> 0 | G6: =SUMIF(A24:A25,"OPEX",O24:O25) -> 0 | H6: =1-(G6/F6) -> #DIV/0!
A7: Number of Sites | C7: =C5+C6 -> 1204 | F7: =SUM(F5:F6) -> 146337.6 | G7: =SUM(G5:G6) -> 102436.32 | H7: =1-(G7/F7) -> 0.3
A8: Remote Spares | C8: 0.03
A9: Total of Spares | C9: =ROUNDUP(C7*C8,0) -> 37
A10: Service Plan | C10: .30/5
A11: Total capacity SES-17 (Mbps) | C11: 0
B12: Overbooking | C12: 0.16666667
A13: Total Ka band Capacity (Mbps) | C13: =C7*35*C12 -> 7023.3333 | F13: Price x Site x Month | G13: Cost x Site x Month | H13: MARGIN
A14: Average Mbps per Site | C14: =C13/C7 -> 5.8333333 | F14: =F7/C7/C19 -> 6.752381 | G14: =G7/C7/C19 -> 4.7266667 | H14: =1-(G14/F14) -> 0.3
B15: #VALUE! | C15: 3.7
A16: Terminal Unit Price (USD) - ExWorks USA | C16: =K25+#REF!+#REF!+#REF! -> #REF!
A17: COST - SES Ka band Mbps / Month (USD) | C17: 125
A18: COST - HUGHES Ka band Mbps / Month (USD) | C18: 40
A19: Contract | C19: 18
A20: % sites with Penalties / month | C20: 0.01
A21: CAPEX Financing Rate | C21: 0.14
A22: UIT | C22: =4950/C15 -> 1337.8378
A24: Type | B24: Category | C24: Subcategory | D24: Manufacturer Part # | E24: Product Code | F24: Description | G24: Qty | H24: Unit of Measure | I24: Discount | J24: Finance? | K24: Unit Price | L24: Unit Disc. Price | M24: Ext. Disc. Price | N24: Unit Cost | O24: Ext. Cost | P24: Profit Margin | Q24: Owner | R24: Monthly Price per Site | S24: Monthly Cost per Site | T24: Monthly Price per Mbps | U24: Monthly Cost per Mbps | V24: Financed CAPEX | W24: Financed Monthly Price per Site | X24: Notes
A25: CAPEX | B25: Hughes Equipment | C25: VSAT | D25: 1505216-0332 | E25: HT2010 | F25: HT2010 Consumer Broadband Satellite Router, Ka Band only | G25: =$C$5 -> 1204 | H25: Unit | I25: 0 | J25: NRC | K25: =Table1[[#This Row],[Unit Cost]]/0.7 -> 121.54286 | L25: =Table1[[#This Row],[Unit Price]]*(1-Table1[[#This Row],[Discount]]) -> 121.54286 | M25: =IF(Table1[[#This Row],[Type]]="OPEX",$C$19,1)*Table1[[#This Row],[Unit Disc. Price]]*Table1[[#This Row],[Qty]] -> 146337.6 | N25: 85.08 | O25: =IF(Table1[[#This Row],[Type]]="OPEX",$C$19,1)*Table1[[#This Row],[Unit Cost]]*Table1[[#This Row],[Qty]] -> 102436.32 | P25: =1-(Table1[[#This Row],[Ext. Cost]]/Table1[[#This Row],[Ext. Disc. Price]]) -> 0.3 | Q25: HNS | R25: =Table1[[#This Row],[Ext. Disc. Price]]/$C$7/$C$19 -> 6.752381 | S25: =Table1[[#This Row],[Ext. Cost]]/$C$7/$C$19 -> 4.7266667 | T25: =Table1[[#This Row],[Ext. Disc. Price]]/$C$13/$C$19 -> 1.157551 | U25: =Table1[[#This Row],[Ext. Cost]]/$C$13/$C$19 -> 0.81028571 | V25: =IF(AND(Table1[[#This Row],[Type]]="CAPEX",Table1[[#This Row],[Finance?]]="MRC"),PMT($C$21/12,$C$19,-Table1[[#This Row],[Ext. Disc. Price]]),0) -> 0 | W25: =IF(AND(Table1[[#This Row],[Type]]="CAPEX",Table1[[#This Row],[Finance?]]="MRC"),PMT($C$21/12,$C$19,-Table1[[#This Row],[Ext. Disc. Price]])/$C$7,IF(Table1[[#This Row],[Type]]="OPEX",Table1[[#This Row],[Ext. Disc. Price]]/$C$7/$C$19,0)) -> 0
A26: CAPEX | B26: Hughes Equipment | C26: VSAT | D26: 1506560-0021+1506561-0021 | E26: ANTENA 90CM | F26: 90cm Ka-Band Saturated Antenna (Single IFL) 1pk | G26: Unit | H26: NRC | L26: =Table1[[#This Row],[Unit Price]]*(1-Table1[[#This Row],[Discount]]) | M26: =IF(Table1[[#This Row],[Type]]="OPEX",$C$19,1)*Table1[[#This Row],[Unit Disc. Price]]*Table1[[#This Row],[Qty]] | O26: =IF(Table1[[#This Row],[Type]]="OPEX",$C$19,1)*Table1[[#This Row],[Unit Cost]]*Table1[[#This Row],[Qty]] | P26: =1-(Table1[[#This Row],[Ext. Cost]]/Table1[[#This Row],[Ext. Disc. Price]]) | R26: =Table1[[#This Row],[Ext. Disc. Price]]/$C$7/$C$19 | S26: =Table1[[#This Row],[Ext. Cost]]/$C$7/$C$19 | T26: =Table1[[#This Row],[Ext. Disc. Price]]/$C$13/$C$19 | U26: =Table1[[#This Row],[Ext. Cost]]/$C$13/$C$19 | V26: =IF(AND(Table1[[#This Row],[Type]]="CAPEX",Table1[[#This Row],[Finance?]]="MRC"),PMT($C$21/12,$C$19,-Table1[[#This Row],[Ext. Disc. Price]]),0) | W26: =IF(AND(Table1[[#This Row],[Type]]="CAPEX",Table1[[#This Row],[Finance?]]="MRC"),PMT($C$21/12,$C$19,-Table1[[#This Row],[Ext. Disc. Price]])/$C$7,IF(Table1[[#This Row],[Type]]="OPEX",Table1[[#This Row],[Ext. Disc. Price]]/$C$7/$C$19,0))
A27: CAPEX | B27: Hughes Equipment | C27: VSAT | D27: 1506560-0021+1506561-0021 | E27: ANTENA 90CM | F27: 90cm Ka-Band Saturated Antenna (Single IFL) 1pk | G27: Unit | H27: NRC | L27: =Table1[[#This Row],[Unit Price]]*(1-Table1[[#This Row],[Discount]]) | M27: =IF(Table1[[#This Row],[Type]]="OPEX",$C$19,1)*Table1[[#This Row],[Unit Disc. Price]]*Table1[[#This Row],[Qty]] | O27: =IF(Table1[[#This Row],[Type]]="OPEX",$C$19,1)*Table1[[#This Row],[Unit Cost]]*Table1[[#This Row],[Qty]] | P27: =1-(Table1[[#This Row],[Ext. Cost]]/Table1[[#This Row],[Ext. Disc. Price]]) | R27: =Table1[[#This Row],[Ext. Disc. Price]]/$C$7/$C$19 | S27: =Table1[[#This Row],[Ext. Cost]]/$C$7/$C$19 | T27: =Table1[[#This Row],[Ext. Disc. Price]]/$C$13/$C$19 | U27: =Table1[[#This Row],[Ext. Cost]]/$C$13/$C$19 | V27: =IF(AND(Table1[[#This Row],[Type]]="CAPEX",Table1[[#This Row],[Finance?]]="MRC"),PMT($C$21/12,$C$19,-Table1[[#This Row],[Ext. Disc. Price]]),0) | W27: =IF(AND(Table1[[#This Row],[Type]]="CAPEX",Table1[[#This Row],[Finance?]]="MRC"),PMT($C$21/12,$C$19,-Table1[[#This Row],[Ext. Disc. Price]])/$C$7,IF(Table1[[#This Row],[Type]]="OPEX",Table1[[#This Row],[Ext. Disc. Price]]/$C$7/$C$19,0))
L28: =Table1[[#This Row],[Unit Price]]*(1-Table1[[#This Row],[Discount]]) | M28: =IF(Table1[[#This Row],[Type]]="OPEX",$C$19,1)*Table1[[#This Row],[Unit Disc. Price]]*Table1[[#This Row],[Qty]] | O28: =IF(Table1[[#This Row],[Type]]="OPEX",$C$19,1)*Table1[[#This Row],[Unit Cost]]*Table1[[#This Row],[Qty]] | P28: =1-(Table1[[#This Row],[Ext. Cost]]/Table1[[#This Row],[Ext. Disc. Price]]) | R28: =Table1[[#This Row],[Ext. Disc. Price]]/$C$7/$C$19 | S28: =Table1[[#This Row],[Ext. Cost]]/$C$7/$C$19 | T28: =Table1[[#This Row],[Ext. Disc. Price]]/$C$13/$C$19 | U28: =Table1[[#This Row],[Ext. Cost]]/$C$13/$C$19 | V28: =IF(AND(Table1[[#This Row],[Type]]="CAPEX",Table1[[#This Row],[Finance?]]="MRC"),PMT($C$21/12,$C$19,-Table1[[#This Row],[Ext. Disc. Price]]),0) | W28: =IF(AND(Table1[[#This Row],[Type]]="CAPEX",Table1[[#This Row],[Finance?]]="MRC"),PMT($C$21/12,$C$19,-Table1[[#This Row],[Ext. Disc. Price]])/$C$7,IF(Table1[[#This Row],[Type]]="OPEX",Table1[[#This Row],[Ext. Disc. Price]]/$C$7/$C$19,0))
L29: =Table1[[#This Row],[Unit Price]]*(1-Table1[[#This Row],[Discount]]) | M29: =IF(Table1[[#This Row],[Type]]="OPEX",$C$19,1)*Table1[[#This Row],[Unit Disc. Price]]*Table1[[#This Row],[Qty]] | O29: =IF(Table1[[#This Row],[Type]]="OPEX",$C$19,1)*Table1[[#This Row],[Unit Cost]]*Table1[[#This Row],[Qty]] | P29: =1-(Table1[[#This Row],[Ext. Cost]]/Table1[[#This Row],[Ext. Disc. Price]]) | R29: =Table1[[#This Row],[Ext. Disc. Price]]/$C$7/$C$19 | S29: =Table1[[#This Row],[Ext. Cost]]/$C$7/$C$19 | T29: =Table1[[#This Row],[Ext. Disc. Price]]/$C$13/$C$19 | U29: =Table1[[#This Row],[Ext. Cost]]/$C$13/$C$19 | V29: =IF(AND(Table1[[#This Row],[Type]]="CAPEX",Table1[[#This Row],[Finance?]]="MRC"),PMT($C$21/12,$C$19,-Table1[[#This Row],[Ext. Disc. Price]]),0) | W29: =IF(AND(Table1[[#This Row],[Type]]="CAPEX",Table1[[#This Row],[Finance?]]="MRC"),PMT($C$21/12,$C$19,-Table1[[#This Row],[Ext. Disc. Price]])/$C$7,IF(Table1[[#This Row],[Type]]="OPEX",Table1[[#This Row],[Ext. Disc. Price]]/$C$7/$C$19,0))
L30: =Table1[[#This Row],[Unit Price]]*(1-Table1[[#This Row],[Discount]]) | M30: =IF(Table1[[#This Row],[Type]]="OPEX",$C$19,1)*Table1[[#This Row],[Unit Disc. Price]]*Table1[[#This Row],[Qty]] | O30: =IF(Table1[[#This Row],[Type]]="OPEX",$C$19,1)*Table1[[#This Row],[Unit Cost]]*Table1[[#This Row],[Qty]] | P30: =1-(Table1[[#This Row],[Ext. Cost]]/Table1[[#This Row],[Ext. Disc. Price]]) | R30: =Table1[[#This Row],[Ext. Disc. Price]]/$C$7/$C$19 | S30: =Table1[[#This Row],[Ext. Cost]]/$C$7/$C$19 | T30: =Table1[[#This Row],[Ext. Disc. Price]]/$C$13/$C$19 | U30: =Table1[[#This Row],[Ext. Cost]]/$C$13/$C$19 | V30: =IF(AND(Table1[[#This Row],[Type]]="CAPEX",Table1[[#This Row],[Finance?]]="MRC"),PMT($C$21/12,$C$19,-Table1[[#This Row],[Ext. Disc. Price]]),0) | W30: =IF(AND(Table1[[#This Row],[Type]]="CAPEX",Table1[[#This Row],[Finance?]]="MRC"),PMT($C$21/12,$C$19,-Table1[[#This Row],[Ext. Disc. Price]])/$C$7,IF(Table1[[#This Row],[Type]]="OPEX",Table1[[#This Row],[Ext. Disc. Price]]/$C$7/$C$19,0))

Sheet Margin Analysis
B2: Number of Sites | C2: ='QTO DB'!C7 -> 1204
B3: Total Mbps | C3: ='QTO DB'!C13 -> 7023.3333
B4: Contract Term | C4: ='QTO DB'!C19 -> 18
B7: MARGIN ANALYSIS SUMMARY
C12: Disct. Ext. Price | D12: Ext. Cost. | E12: % of Project | F12: Monthly Price / Site | G12: Monthly Cost / Site | H12: Monthly Price / Mbps | I12: Monthly Cost / Mbps | J12: Margin
B13: CAPEX | C13: 146.3376 | D13: 102.43632 | E13: 1 | F13: 6.752381 | G13: 4.7266667 | H13: 1.157551 | I13: 0.81028571 | J13: 0.3
B14: Hughes Equipment | C14: 146.3376 | D14: 102.43632 | E14: 1 | F14: 6.752381 | G14: 4.7266667 | H14: 1.157551 | I14: 0.81028571 | J14: 0.3
B15: VSAT | C15: 146.3376 | D15: 102.43632 | E15: 1 | F15: 6.752381 | G15: 4.7266667 | H15: 1.157551 | I15: 0.81028571 | J15: 0.3
B16: Total general | C16: 146.3376 | D16: 102.43632 | E16: 1 | F16: 6.752381 | G16: 4.7266667 | H16: 1.157551 | I16: 0.81028571 | J16: 0.3

Sheet Customer View
A1: QUOTE
E2: Quote #: | F2: QTO_000XXXX-00
E3: Date: | F3: =TODAY() -> 45869
E5: DO NOT DISTRIBUTE
A8: Prepared For: | B8: ='QTO DB'!$C$2 -> MINEDU | D8: Prepared By: | E8: ='QTO DB'!$C$4 -> JUAN ASTO
A11: Monthly Recurring Payment per Site
C12: Finance? | D12: NRC
A14: Service | B14: Sites | C14: Monthly Price per Site
A15: Unlimited Satellite Internet Service (Includes 74cm ant.,2W Radio and HT2000W IDU) | B15: ='QTO DB'!C7 -> 1204 | C15: 0
A17: One Time Payment
A18: Finance? | B18: NRC
A20: Item | B20: Qty | C20: Unit Price | D20: Discount | E20: Unit Disc. Price | F20: Ext. Disc. Price
A21: VSAT | C21: 121.54286 | D21: 0 | E21: 121.54286 | F21: 146337.6
A22: HT2010 Consumer Broadband Satellite Router, Ka Band only | B22: 1204 | C22: 121.54286 | D22: 0 | E22: 121.54286 | F22: 146337.6
A23: Total general | C23: 121.54286 | D23: 0 | E23: 121.54286 | F23: 146337.6
A54: 4)
A55: 5)
A56: 6)
A57: 7)
A58: 8)
A59: 9)
A60: 10)
A61: 11)
A62: 12)
